<?xml version="1.0"?>
<!DOCTYPE archimedes SYSTEM "../dtd/archimedes.dtd" >
<archimedes xmlns:xlink="http://www.w3.org/1999/xlink">      <info>
	<author>Epicurus</author>
	<title>Varia</title>
	<date>1566</date>
	<place>Antwerp</place>
	<translator/>
	<lang>el</lang>
	<cvs_file>epicu_physi_104_el_1566.xml</cvs_file>
	<cvs_version/>
	<comments>From Gifanius' 1566 edition of Lucretius lucre_natur_079_la_1566.xml; the letter to Herodotus; a canon of Epicurus; and the letter to Pythocles</comments>
	<locator>104.xml</locator>
</info>      <text>          <front>          </front>          <body>
<chap>
<pb pagenum="235"/>
<p><s>*)epi/kouros *(hrodo/tw| xai/rein. <!-- ref: t,1 --><lb/>
</s></p><p><s>*toi=s mh\ duname/nois, w)= *(hro/dote, e(/ka&shy;<lb/>sta tw=n peri\ fu/sews h(mi=n<!-- ref: 35,1 -->
a)nagegram<lb/>me/nwn e)cakribou=n mhde\ ta\s mei/zous <lb/>tw=n sunte<!-- ref: 35,2 -->
tagme/nwn bi/blous diaqrei=n, e)pitomh\n <lb/>th=s o(/lhs pragmatei/as ei)s <!-- ref: 35,3 -->
to\ katasxei=n tw=n o(lo&shy;<lb/>sxerwta/twn docw=n th\n mnh/mhn i(kanw=s au)<!-- ref: 35,4 -->toi=s <lb/>pareskeu/asa, i(/na par' e(ka/stous tw=n kairw=n e)n toi=s <lb/>kuriw<!-- ref: 35,5 -->ta/tois bohqei=n au(toi=s du/nwntai, kaq' o(/son <lb/>a)\n e)fa/ptwntai th=s <!-- ref: 35,6 -->peri\ fu/sews qewri/as. </s>
<s>kai\ tou\s <lb/>probebhko/tas de\ i(kanw=s e)n th=| <!-- ref: 35,7 -->tw=n o(/lwn e)pible<lb/>/yei to\n tu/pon th=s o(/lhs pragmatei/as to\n kate&shy;<!-- ref: 35,8 --><lb/>
stoixeiwme/non dei= mnhmoneu/ein: th=s ga\r a)qro/as e)pi&shy;<lb/>bolh=s pukno\n <!-- ref: 35,9 -->deo/meqa, th=s de\ kata\ me/ros ou)x <lb/>o(moi/ws. </s>
<s><!-- ref: 35,10 -->badiste/on me\n ou)=n kai\<!-- ref: 36,1 --> e)p' e)kei=na sune&shy;<lb/>xw=s, e)n th=| mnh/mh|. </s>
<s>tosou=to poihte/on, a)f'<!-- ref: 36,2 -->ou(= h(/ te <lb/>
kuriwta/th e)pibolh\ e)pi\ ta\ pra/gmata e)/stai kai\ <lb/>dh\ kai\ to\ <!-- ref: 36,3 -->kata\ me/ros a)kri/bwma pa=n e)ceurh/se&shy;<lb/>tai, tw=n o(losxerwta/twn tu<!-- ref: 36,4 --><lb/>pwn eu)= perieilhmme&shy;<lb/>/nwn kai\ mnhmoneuome/nwn. </s>
<s>e)pei\ kai\ tw=| tete<!-- ref: 36,5 -->lesiourgh&shy;<lb/>me/nw| tou=to kuriw/taton tou= panto\s a)kribw/matos gi/ne&shy;<!-- ref: 36,6 --><lb/>
tai, to\ tai=s e)pibolai=s o)ce/ws du/nasqai kai\ <!-- ref: 36,7 -->pro\s <lb/>a(pla= stoixeiw/mata kai\ fwna\s suna<!-- ref: 36,8 -->gome/nwn. </s>
<s>ou) <lb/>ga\r oi(=o/n te to\ pu/knwma th=s sunexou=s tw=n o(/lwn <!-- ref: 36,9 -->peri&shy;<lb/>odei/as ei)=nai mh\ duname/nou dia\ braxew=n fwnw=n <lb/>a(/pan e)mperi&shy;<!-- ref: 36,10 -->labei=n e)n au(tw=| to\ kata\ me/ros a)\n <lb/>e)cakribwqe/n. </s>
<s><!-- ref: 36,11 -->o(/qen dh\ <!-- ref: 37,1 -->pa=si xrhsi/mhs ou)/shs toi=s <lb/> w)|keiwme/nois fusiologi/a|, th=s toiau/ths <!-- ref: 37,2 -->
o(dou=, par<pb pagenum="236"/>egguw=n to\ sunexe\s e)ne/rghma e)n fusiologi/a| kai\ toiou/tw| <!-- ref: 37,3 --><lb/>
ma/lista e)ggalhni/zon tw=| bi/w| poih/sasqai, kai\ toiau/thn tina\ e)pi&shy;<!-- ref: 37,4 --><lb/>
tomh\n &lt;sune/qhka&gt; kai\ stoixei/wsin tw=n o(/lwn docw=n. <!-- ref: 37,5 --><lb/>
</s></p><p><s>*prw=ton me\n ou)=n ta\ u(potetagme/na toi=s fqo/ggois, w)= *(hro/do&shy;<!-- ref: 37,6 --><lb/>
te, dei= ei)lhfe/nai, o(/pws a)\n ta\ docazo/mena h)\ zhtou/mena h)\ a)po&shy;<!-- ref: 37,7 --><lb/>
rou/mena e)/xwmen ei)s tau=ta a)nagago/ntes e)pikri/nein, kai\ mh\ a)/kri&shy;<!-- ref: 37,8 --><lb/>
ta pa/nta h(mi=n &lt;h)=|&gt; ei)s a)/peiron a)podeiknu/ousin h)\ kenou\s fqo/g&shy;<!-- ref: 37,9 --><lb/>
gous e)/xwmen: <!-- ref: 37,10 --><lb/>
a)na/gkh ga\r to\ prw=ton e)nno/hma kaq' e(/kaston <!-- ref: 38,1 --><lb/>
fqo/ggon ble/pesqai kai\ mhqe\n a)podei/cews prosdei=sqai, ei)/per <!-- ref: 38,2 --><lb/>
e(/comen to\ zhtou/menon h)\ a)porou/menon kai\ docazo/menon e)f' o(\ a)na/&shy;<!-- ref: 38,3 --><lb/>
comen. </s><s>*ei)=ta kata\ ta\s ai)sqh/seis dei= pa/nta threi=n kai\ a(plw=s ta\s <!-- ref: 38,4 --><lb/>
parou/sas e)pibola\s ei)/te dianoi/as ei)/q' o(/tou dh/pote tw=n krithri/wn, <!-- ref: 38,5 --><lb/>
o(moi/ws de\ kai\ ta\ u(pa/rxonta pa/qh, o(/pws a)\n kai\ to\ prosme/non <!-- ref: 38,6 --><lb/>
kai\ to\ a)/dhlon e)/xwmen oi(=s shmeiwso/meqa, tau=ta de\ dialabo/ntas <!-- ref: 38,7 --><lb/>
sunora=n h)/dh peri\ tw=n a)dh/lwn. </s><s>*prw=ton me\n o(/ti ou)de\n gi/netai e)k <!-- ref: 38,8 --><lb/>
tou= mh\ o)/ntos: pa=n ga\r e)k panto\s e)gi/net' a)\n sperma/twn ge ou)qe\n <!-- ref: 38,9 --><lb/>
prosdeo/menon. </s><s><!-- ref: 38,10 --><lb/>
kai\ ei) e)fqei/reto de\ to\ a)fanizo/menon ei)s to\ mh\ <!-- ref: 39,1 --><lb/>
o)/n, pa/nta a)\n a)pwlw/lei ta\ pra/gmata, ou)k o)/ntwn tw=n ei)s a(\ die&shy; <!-- ref: 39,2 --><lb/>
lu/eto. </s><s>*kai\ mh\n kai\ to\ pa=n a)ei\ toiou=ton h)=n oi(=on nu=n e)sti, kai\ a)ei\ <!-- ref: 39,3 --><lb/>
toiou=ton e)/stai. </s><s>ou)qe\n ga/r e)stin ei)s o(\ metabalei=. </s><s>para\ ga\r to\ <!-- ref: 39,4 --><lb/>
pa=n ou)qe/n e)stin, o(\ a)\n ei)selqo\n ei)s au)to\ th\n metabolh\n poih/&shy;<!-- ref: 39,5 --><lb/>
saito. <!-- ref: 39,6 --><lb/>
</s></p><p><s>*)alla\ mh\n kai\ &lpar;tou=to kai\ e)n th=| *mega/lh| e)pitomh=| <!-- ref: 39,7 --><lb/>
fhsi kat' a)rxh/n, kai\ e)n th=| &lt;a&gt; </s><s>*peri\ fu/sews&rpar; to\ pa=n e)sti <!-- ref: 39,8 --><lb/>
&lt;sw/mata kai\ keno/n&gt;. </s><s>sw/mata me\n ga\r w(s e)/stin, au)th\ h( ai)/sqh&shy;<!-- ref: 39,9 --><lb/>
sis e)pi\ pa/ntwn mar<pb pagenum="237"/>turei=, kaq' h(/n a)nagkai=on to\ a)/dhlon tw=| logi&shy;<!-- ref: 39,10 --><lb/>
smw=| tekmai/resqai, w(/sper proei=pon to\ pro/sqen. </s><s><!-- ref: 39,11 --><lb/>
ei) &lt;de\&gt; mh\ h)=n <!-- ref: 40,1 --><lb/>
o(\ keno\n kai\ xw/ran kai\ a)nafh= fu/sin o)noma/zomen, ou)k a)\n ei)=xe ta\ <!-- ref: 40,2 --><lb/>
sw/mata o(/pou h)=n ou)de\ di' ou(= e)kinei=to, kaqa/per fai/netai kinou/&shy;<!-- ref: 40,3 --><lb/>
mena: para\ de\ tau=ta ou)qe\n ou)d' e)pinohqh=nai du/natai ou)/te peri&shy;<!-- ref: 40,4 --><lb/>
lhptw=s ou)t' a)nalo/gws toi=s perilhptoi=s, w(s kaq' o(/las fu/seis <!-- ref: 40,5 --><lb/>
lambano/mena kai\ mh\ w(s ta\ tou/twn sumptw/mata h)\ sumbebhko/ta <!-- ref: 40,6 --><lb/>
lego/mena. </s><s>*kai\ mh\n kai\ tw=n &lpar;tou=to kai\ e)n th=| prw/th| <!-- ref: 40,7 --><lb/>
*peri\ fu/sews kai\ e)n th=| &lt;i&gt; </s><s>&lt;d&gt; </s><s>kai\ &lt;i&gt; </s><s>&lt;e&gt; </s><s>kai\ <!-- ref: 40,8 --><lb/>
th=| *mega/lh| e)pitomh=|&rpar; swma/twn ta\ me/n e)sti sugkri/seis ta\ d' e)c <!-- ref: 40,9 --><lb/>
w(=n ai( sugkri/seis pepoi/hntai: <!-- ref: 40,10 --><lb/>
tau=ta de/ e)stin a)/toma kai\ a)meta/&shy;<!-- ref: 41,1 --><lb/>
blhta, ei)/per mh\ me/llei pa/nta ei)s to\ mh\ o)\n fqarh/sesqai, a)ll' <!-- ref: 41,2 --><lb/>
i)sxu/onta u(pomenei=n e)n tai=s dialu/sesi tw=n sugkri/sewn plh/rh <!-- ref: 41,3 --><lb/>
th\n fu/sin o)/nta kai\ ou)k e)/xonta o(/ph| h)\ o(/pws dialuqh/setai. </s><s>w(/ste <!-- ref: 41,4 --><lb/>
ta\s a)rxa\s a)to/mous a)nagkai=on ei)=nai swma/twn fu/seis. <!-- ref: 41,5 --><lb/>
</s></p><p><s>*)alla\ mh\n kai\ to\ pa=n a)/peiro/n e)sti: to\ ga\r peperasme/non <!-- ref: 41,6 --><lb/>
a)/kron e)/xei: to\ de\ a)/kron par' e(/tero/n ti qewrei=tai: &lt;a)lla\ mh\n to\ <!-- ref: 41,7 --><lb/>
pa=n ou) par' e(/tero/n ti qewrei=tai:&gt; w(/ste ou)k e)/xon a)/kron pe/ras <!-- ref: 41,8 --><lb/>
ou)k e)/xei: pe/ras de\ ou)k e)/xon a)/peiron a)\n ei)/h kai\ ou) peperasme/non.  <!-- ref: 41,9 --><lb/>
</s></p><p><s>*kai\ mh\n kai\ tw=| plh/qei tw=n swma/twn a)/peiro/n e)sti to\ pa=n <!-- ref: 41,10 --><lb/>
kai\ tw=| mege/qei tou= kenou=: <!-- ref: 41,11 --><lb/>
ei)/ te ga\r h)=n to\ keno\n a)/peiron, ta\ <!-- ref: 42,1 --><lb/>
de\ sw/mata w(risme/na, ou)qamou= a)\n e)/mene ta\ sw/mata, a)ll' e)fe/&shy;<!-- ref: 42,2 --><lb/>
reto kata\ to\ a)/peiron keno\n diesparme/na, ou)k e)/xonta ta\ u(pe&shy;<!-- ref: 42,3 --><lb/>
rei/don<pb pagenum="238"/>ta kai\ ste/llonta kata\ ta\s a)nakopa/s: ei)/ te to\ keno\n h)=n <!-- ref: 42,4 --><lb/>
w(risme/non, ou)k a)\n ei)=xe ta\ a)/peira sw/mata o(/pou e)ne/sth. <!-- ref: 42,5 --><lb/>
</s></p><p><s>*pro/s te tou/tois ta\ a)/toma tw=n swma/twn kai\ mesta/, e)c w(=n <!-- ref: 42,6 --><lb/>
kai\ ai( sugkri/seis gi/nontai kai\ ei)s a(\ dialu/ontai, a)peri/lhpta/ e)sti <!-- ref: 42,7 --><lb/>
tai=s diaforai=s tw=n sxhma/twn: ou) ga\r dunato\n gene/sqai ta\s <!-- ref: 42,8 --><lb/>
tosau/tas diafora\s e)k tw=n au)tw=n sxhma/twn perieilhmme/nwn. </s><s><!-- ref: 42,9 --><lb/>
kai\ kaq' e(ka/sthn de\ sxhma/tisin a(plw=s a)/peiroi/ ei)sin ai( o(/moiai, <!-- ref: 42,10 --><lb/>
tai=s de\ diaforai=s ou)x a(plw=s a)/peiroi, a)lla\ mo/non a)peri/lhptoi, <!-- ref: 42,11 --><lb/>
&lpar;ou)de\ ga/r fhsin e)ndote/rw ei)s a)/peiron th\n tomh\n tugxa/nein. </s><s><!-- ref: 43,1 --><lb/>
le/gei de/, e)peidh\ ai( poio/thtes metaba/llontai&rpar; ei) me/llei tis mh\ <!-- ref: 43,2 --><lb/>
kai\ toi=s mege/qesin a(plw=s ei)s a)/peiron au)ta\s e)kba/llein. <!-- ref: 43,3 --><lb/>
</s></p><p><s>*kinou=ntai/ te sunexw=s ai( a)/tomoi &lpar;fhsi\ de\ e)ndote/rw kai\ i)so&shy;<!-- ref: 43,4 --><lb/>
taxw=s au)ta\s kinei=sqai tou= kenou= th\n ei)=cin o(moi/an parexome/nou <!-- ref: 43,5 --><lb/>
kai\ th=| koufota/th| kai\ th=| baruta/th|&rpar; to\n ai)w=na, kai\ ai( me\n ei)s <!-- ref: 43,6 --><lb/>
makra\n a)p' a)llh/lwn diista/menai, ai( de\ au)tou= to\n palmo\n i)/sxu&shy;<!-- ref: 43,7 --><lb/>
sai, o(/tan tu/xwsi th=| periplokh=| kekleime/nai h)\ stegazo/menai <!-- ref: 43,8 --><lb/>
para\ tw=n plektikw=n. </s><s><!-- ref: 43,9 --><lb/>
h(/ te ga\r tou= kenou= fu/sis h( diori/zousa <!-- ref: 44,1 --><lb/>
e(ka/sthn au)th\n tou=to paraskeua/zei, th\n u(pe/reisin ou)x oi(/a te <!-- ref: 44,2 --><lb/>
ou)=sa poiei=sqai: h(/ te stereo/ths h( u(pa/rxousa au)tai=s kata\ th\n <!-- ref: 44,3 --><lb/>
su/gkrousin to\n a)popalmo\n poiei=, e)f' o(po/son a)\n h( periplokh\ <!-- ref: 44,4 --><lb/>
th\n a)pokata/stasin e)k th=s sugkrou/sews didw=|. </s><s>a)rxh\ de\ tou/twn <!-- ref: 44,5 --><lb/>
ou)k e)/stin, a)idi/wn tw=n a)to/mwn ou)sw=n kai\ tou= kenou=. </s><s>&lpar;fhsi\ d' <!-- ref: 44,6 --><lb/>
e)ndote/rw mhde\ poio/thta/ tina peri\ ta\s a)to/mous ei)=nai plh\n sxh/&shy;<!-- ref: 44,7 --><lb/>
matos kai\ mege/<pb pagenum="239"/>qous kai\ ba/rous: to\ de\ xrw=ma para\ th\n qe/sin  <!-- ref: 44,8 --><lb/>
tw=n a)to/mwn a)lla/ttesqai e)n tai=s *dw/deka stoixeiw/&shy;<!-- ref: 44,9 --><lb/>
sesi/ fhsi. pa=n te me/geqos mh\ ei)=nai peri\ au)ta/s: ou)de/pote gou=n <!-- ref: 44,10 --><lb/>
a)/tomos w)/fqh ai)sqh/sei.&rpar; <!-- ref: 44,11 --><lb/>
</s></p><p><s>*(h tosau/th dh\ fwnh\ tou/twn pa/ntwn mnhmoneuome/nwn to\n <!-- ref: 45,1 --><lb/>
i(kano\n tu/pon u(poba/llei th=s tw=n o)/ntwn fu/sews e)pinoi/as. <!-- ref: 45,2 --><lb/>
</s></p><p><s>*)alla\ mh\n kai\ ko/smoi a)/peiroi/ ei)sin, oi(/ q' o(/moioi tou/tw| kai\ <!-- ref: 45,3 --><lb/>
a)no/moioi. </s><s>ai(/ te ga\r a)/tomoi a)/peiroi ou)=sai, w(s a)/rti a)pedei/xqh, <!-- ref: 45,4 --><lb/>
fe/rontai kai\ porrw/tatw: ou) ga\r katanh/lwntai ai( toiau=tai <!-- ref: 45,5 --><lb/>
a)/tomoi, e)c w(=n a)\n ge/noito ko/smos h)\ u(f' w(=n a)\n poihqei/h, ou)/t' <!-- ref: 45,6 --><lb/>
ei)s e(/na ou)/t' ei)s peperasme/nous, ou)/q' o(/soi toiou=toi ou)/q' o(/soi <!-- ref: 45,7 --><lb/>
dia/foroi tou/tois. </s><s>w(/ste ou)de\n to\ e)mpodostath=so/n e)sti pro\s th\n <!-- ref: 45,8 --><lb/>
a)peiri/an tw=n ko/smwn. <!-- ref: 45,9 --><lb/>
</s></p><p><s>*kai\ mh\n kai\ tu/poi o(moiosxh/mones toi=s steremni/ois ei)si/, <!-- ref: 46,1 --><lb/>
lepto/thsin a)pe/xontes makra\n tw=n fainome/nwn. </s><s>ou)/te ga\r a)po&shy;<!-- ref: 46,2 --><lb/>
sta/seis a)dunatou=si e)n tw=| perie/xonti gi/nesqai toiau=tai ou)/t' <!-- ref: 46,3 --><lb/>
e)pithdeio/thtes pro\s katergasi/as tw=n koilwma/twn kai\ leioth/&shy;<!-- ref: 46,4 --><lb/>
tw=n [gi/nesqai], ou)/te a)po/rroiai th\n e(ch=s qe/sin kai\ ba/sin dia&shy;<!-- ref: 46,5 --><lb/>
throu=sai, h(/nper kai\ e)n toi=s steremni/ois ei)=xon: tou/tous de\ tou\s <!-- ref: 46,6 --><lb/>
tu/pous ei)/dwla prosagoreu/omen. </s><s>kai\ mh\n kai\ h( dia\ tou= kenou= <!-- ref: 46,7 --><lb/>
fora\ kata\ mhdemi/an a)pa/nthsin tw=n a)ntikoya/ntwn ginome/nh pa=n <!-- ref: 46,8 --><lb/>
mh=kos perilhpto\n e)n a)perinoh/tw| xro/nw| suntelei=. </s><s>bra/dous ga\r <!-- ref: 46,9 --><lb/>
kai\ ta/xous a)ntikoph\ kai\ ou)k a)ntikoph\ o(moi/wma lamba/nei. </s><s><!-- ref: 46,10 --><lb/>
ou) mh\n ou)de\ <pb pagenum="240"/>a(/ma kata\ tou\s dia\ lo/gou qewrhtou\s xro/nous <!-- ref: 47,1 --><lb/>
au)to\ to\ fero/menon sw=ma e)pi\ tou\s plei/ous to/pous a)fiknei=tai <!-- ref: 47,2 --><lb/>
_a)diano/hton ga/r_kai\ tou=to sunafiknou/menon e)n ai)sqhtw=| <!-- ref: 47,3 --><lb/>
xro/nw| o(/qen dh/poqen tou= a)pei/rou ou)k e)c ou(= a)\n perila/bwmen  <!-- ref: 47,4 --><lb/>
th\n fora\n to/pou e)/stai a)fista/menon: a)ntikoph=| ga\r o(/moion e)/stai, <!-- ref: 47,5 --><lb/>
ka)\n me/xri tosou/tou to\ ta/xos th=s fora=s mh\ a)ntikope\n katali/&shy;<!-- ref: 47,6 --><lb/>
pwmen: xrh/simon dh\ kai\ tou=to katasxei=n to\ stoixei=on. </s><s>ei)=q' o(/ti <!-- ref: 47,7 --><lb/>
ta\ ei)/dwla tai=s lepto/thsin a)nuperblh/tois ke/xrhtai ou)qe\n a)nti&shy;<!-- ref: 47,8 --><lb/>
marturei= tw=n fainome/nwn: o(/qen kai\ ta/xh a)nupe/rblhta e)/xei, <!-- ref: 47,9 --><lb/>
pa/nta po/ron su/mmetron e)/xonta pro\s to\ a)pei/rois au)tw=n mhqe\n <!-- ref: 47,10 --><lb/>
a)ntiko/ptein h)\ o)li/ga a)ntiko/ptein % pollai=s de\ kai\ a)pei/rois <!-- ref: 47,11 --><lb/>
eu)qu\s a)ntiko/ptein ti %. </s><s><!-- ref: 47,12 --><lb/>
pro/s te tou/tois o(/ti h( ge/nesis tw=n <!-- ref: 48,1 --><lb/>
ei)dw/lwn a(/ma noh/mati sumbai/nei: kai\ ga\r r(eu=sis a)po\ tw=n sw&shy;<!-- ref: 48,2 --><lb/>
ma/twn tou= e)pipolh=s sunexh/s, ou)k e)pi/dhlos th=| meiw/sei dia\ th\n <!-- ref: 48,3 --><lb/>
a)ntanaplh/rwsin, sw/|zousa th\n e)pi\ tou= steremni/ou qe/sin kai\ <!-- ref: 48,4 --><lb/>
ta/cin tw=n a)to/mwn e)pi\ polu\n xro/non, ei) kai\ e)ni/ote sugxeome/nh <!-- ref: 48,5 --><lb/>
u(pa/rxei, kai\ susta/seis e)n tw=| perie/xonti o)cei=ai dia\ to\ mh\ dei=n <!-- ref: 48,6 --><lb/>
kata\ ba/qos to\ sumplh/rwma gi/nesqai, kai\ a)/lloi de\ tro/poi <!-- ref: 48,7 --><lb/>
tine\s gennhtikoi\ tw=n toiou/twn fu/sew/n ei)sin. </s><s>ou)qe\n ga\r tou/twn <!-- ref: 48,8 --><lb/>
a)ntimarturei=tai tai=s ai)sqh/sesin, a)\n ble/ph| tis ti/na tro/pon ta\s <!-- ref: 48,9 --><lb/>
e)nargei/as, &lt;t&gt;i/na kai\ ta\s sumpaqei/as a)po\ tw=n e)/cwqen pro\s <!-- ref: 48,10 --><lb/>
h(ma=s a)noi/sei. <!-- ref: 48,11 --><lb/>
</s></p><p><s>*dei= de\ kai\ nomi/zein e)peisio/ntos tino\s a)po\ tw=n e)/cwqen ta\s <!-- ref: 49,1 --><lb/>
morfa\s o(ra=n h(ma=s kai\ dianoei=sqai: ou) ga\r a)\n apo<pb pagenum="241"/>sfragi/saito <!-- ref: 49,2 --><lb/>
ta\ e)/cw th\n e(autw=n fu/sin tou= te xrw/matos kai\ th=s morfh=s dia\ <!-- ref: 49,3 --><lb/>
tou= a)e/ros tou= metacu\ h(mw=n te ka)kei/nwn, ou)de\ dia\ tw=n a)kti/- <!-- ref: 49,4 --><lb/>
nwn h)\ w(=n dh/pote r(euma/twn a)f' h(mw=n pro\s e)kei=na paragino&shy;<!-- ref: 49,5 --><lb/>
me/nwn, ou(/tws w(s tu/pwn tinw=n e)peisio/ntwn h(mi=n a)po\ tw=n prag&shy;<!-- ref: 49,6 --><lb/>
ma/twn o(moxro/wn te kai\ o(moiomo/rfwn kata\ to\ e)narmo/tton me/&shy;<!-- ref: 49,7 --><lb/>
geqos ei)s th\n o)/yin h)\ th\n dia/noian, w)ke/ws tai=s forai=s xrwme/nwn, <!-- ref: 49,8 --><lb/>
ei)=ta dia\ tau/thn th\n ai)ti/an tou= e(no\s kai\ sunexou=s th\n fanta&shy;<!-- ref: 50,1 --><lb/>
si/an a)podido/ntwn kai\ th\n sumpa/qeian a)po\ tou= u(pokeime/nou sw|&shy;<!-- ref: 50,2 --><lb/>
zo/ntwn kata\ to\n e)kei=qen su/mmetron e)pereismo\n e)k th=s kata\ <!-- ref: 50,3 --><lb/>
ba/qos e)n tw=| steremni/w| tw=n a)to/mwn pa/lsews. </s><s>kai\ h(\n a)\n la/bw&shy;<!-- ref: 50,4 --><lb/>
men fantasi/an e)piblhtikw=s th=| dianoi/a| h)\ toi=s ai)sqhthri/ois ei)/te <!-- ref: 50,5 --><lb/>
morfh=s ei)/te sumbebhko/twn, morfh/ e)stin au(/th tou= steremni/ou, <!-- ref: 50,6 --><lb/>
ginome/nh kata\ to\ e(ch=s pu/knwma h)\ e)gkata/leimma tou= ei)dw/lou. <!-- ref: 50,7 --><lb/>
</s></p><p><s>[*to\ de\ yeu=dos kai\ to\ dihmarthme/non e)n tw=| prosdocazo&shy;<!-- ref: 50,8 --><lb/>
me/nw| a)ei/ e)stin &lt;e)pi\ tou= prosme/nontos&gt; e)pimarturhqh/sesqai h)\ <!-- ref: 50,9 --><lb/>
mh\ a)ntimarturhqh/sesqai, ei)=t' ou)k e)pimarturoume/nou &lt;h)\ a)nti&shy;<!-- ref: 50,10 --><lb/>
marturoume/nou&gt; kata/ tina ki/nhsin e)n h(mi=n au)toi=s sunhmme/nhn <!-- ref: 50,11 --><lb/>
th=| fantastikh=| e)pibolh=|, dia/lhyin de\ e)/xousan, kaq' h(\n to\ yeu=dos <!-- ref: 50,12 --><lb/>
gi/netai]. </s><s><!-- ref: 50,13 --><lb/>
h(/ te ga\r o(moio/ths tw=n fantasmw=n oi(onei\ e)n ei)ko/ni <!-- ref: 51,1 --><lb/>
lambanome/nwn h)\ kaq' u(/pnous ginome/nwn h)\ kat' a)/llas tina\s e)pi&shy;<!-- ref: 51,2 --><lb/>
bola\s th=s dianoi/as h)\ tw=n loipw=n krithri/wn ou)k a)/n pote u(ph=rxe <!-- ref: 51,3 --><lb/>
toi=s ou)=si/ te kai\ a)lhqe/si prosagoreuome/nois, ei) mh\ h)=n tina kai\ <!-- ref: 51,4 --><lb/>
tau=ta pro\s a(\ &lt;e)pi&gt;ba/llomen: to\ de\ dihmarthme/non ou)k a)\n u(ph=r&shy;<!-- ref: 51,5 --><lb/>
xen, ei) mh\ e)lamba/nomen <pb pagenum="242"/>kai\ a)/llhn tina\ ki/nhsin e)n h(mi=n au)toi=s <!-- ref: 51,6 --><lb/>
sunhmme/nhn me\n &lt;th=| fantastikh=| e)pibolh=|&gt;, dia/lhyin de\ e)/xousan: <!-- ref: 51,7 --><lb/>
kata\ de\ tau/thn [th\n sunhmme/nhn th=| fantastikh=| e)pibolh=|, dia/- <!-- ref: 51,8 --><lb/>
lhyin de\ e)/xousan], e)a\n me\n mh\ e)pimarturhqh=| h)\ a)ntimarturhqh=|, <!-- ref: 51,9 --><lb/>
to\ yeu=dos gi/netai: e)a\n de\ e)pimarturhqh=| h)\ mh\ a)ntimarturhqh=|, <!-- ref: 51,10 --><lb/>
to\ a)lhqe/s. </s><s><!-- ref: 51,11 --><lb/>
kai\ tau/thn ou)=n sfo/dra ge dei= th\n do/can kate/xein, <!-- ref: 52,1 --><lb/>
i(/na mh/te ta\ krith/ria a)nairh=tai ta\ kata\ ta\s e)nargei/as mh/te <!-- ref: 52,2 --><lb/>
to\ dihmarthme/non o(moi/ws bebaiou/menon pa/nta suntara/tth|. <!-- ref: 52,3 --><lb/>
</s></p><p><s>*)alla\ mh\n kai\ to\ a)kou/ein gi/netai r(eu/mato/s tinos ferome/nou <!-- ref: 52,4 --><lb/>
a)po\ tou= fwnou=ntos h)\ h)xou=ntos h)\ yofou=ntos h)\ o(/pws dh/pote <!-- ref: 52,5 --><lb/>
a)koustiko\n pa/qos paraskeua/zontos. </s><s>to\ de\ r(eu=ma tou=to ei)s <!-- ref: 52,6 --><lb/>
o(moiomerei=s o)/gkous diaspei/retai, a(/ma tina\ diasw/|zontas sumpa/&shy;<!-- ref: 52,7 --><lb/>
qeian pro\s a)llh/lous kai\ e(no/thta i)dio/tropon, diatei/nousan pro\s <!-- ref: 52,8 --><lb/>
to\ a)postei=lan kai\ th\n e)pai/sqhsin th\n e)p' e)kei/nou w(s ta\ polla\ <!-- ref: 52,9 --><lb/>
poiou=san, ei) de\ mh/ ge, to\ e)/cwqen mo/non e)/ndhlon paraskeua/zou&shy;<!-- ref: 52,10 --><lb/>
san: <!-- ref: 52,11 --><lb/>
a)/neu ga\r a)naferome/nhs tino\s e)kei=qen sumpaqei/as ou)k a)\n <!-- ref: 53,1 --><lb/>
ge/noito h( toiau/th e)pai/sqhsis. </s><s>ou)k au)to\n ou)=n dei= nomi/zein to\n <!-- ref: 53,2 --><lb/>
a)e/ra u(po\ th=s proieme/nhs fwnh=s h)\ kai\ tw=n o(mogenw=n sxhmati/ze&shy;<!-- ref: 53,3 --><lb/>
sqai_pollh\n ga\r e)/ndeian e(/cei tou=to pa/sxwn u(p' e)kei/nhs_ <!-- ref: 53,4 --><lb/>
a)ll' eu)qu\s th\n ginome/nhn plhgh\n e)n h(mi=n, o(/tan fwnh\n a)fi/wmen, <!-- ref: 53,5 --><lb/>
toiau/thn e)/kqliyin o)/gkwn tinw=n r(eu/matos pneumatw/dous a)pote&shy;<!-- ref: 53,6 --><lb/>
lestikw=n poiei=sqai, h(\ to\ pa/qos to\ a)koustiko\n h(mi=n para&shy;<!-- ref: 53,7 --><lb/>
skeua/zei. <!-- ref: 53,8 --><lb/>
</s></p><p><s>*kai\ mh\n kai\ th\n o)smh\n nomiste/on, w(/sper kai\ th\n a)koh\n <!-- ref: 53,9 --><lb/>
ou)k a)/n pote ou)qe\n pa/qos e)rga/sasqai, ei) mh\ o)/gkoi tine\s h)=san <!-- ref: 53,10 --><lb/>
a)po\ tou= pra/gmatos a)pofero/menoi, <pb pagenum="243"/>su/mmetroi pro\s tou=to to\ <!-- ref: 53,11 --><lb/>
ai)sqhth/rion kinei=n, oi( me\n toi=oi tetaragme/nws kai\ a)llotri/ws, <!-- ref: 53,12 --><lb/>
oi( de\ toi=oi a)tara/xws kai\ oi)kei/ws e)/xontes.  <!-- ref: 53,13 --><lb/>
</s></p><p><s>*kai\ mh\n kai\ ta\s a)to/mous nomiste/on mhdemi/an poio/thta tw=n <!-- ref: 54,1 --><lb/>
fainome/nwn prosfe/resqai plh\n sxh/matos kai\ ba/rous kai\ me&shy;<!-- ref: 54,2 --><lb/>
ge/qous kai\ o(/sa e)c a)na/gkhs sxh/matos sumfuh= e)sti. </s><s>poio/ths <!-- ref: 54,3 --><lb/>
ga\r pa=sa metaba/llei: ai( de\ a)/tomoi ou)de\n metaba/llousin, e)pei&shy;<!-- ref: 54,4 --><lb/>
dh/ per dei= ti u(pome/nein e)n tai=s dialu/sesi tw=n sugkri/sewn ste&shy;<!-- ref: 54,5 --><lb/>
reo\n kai\ a)dia/luton, o(\ ta\s metabola\s ou)k ei)s to\ mh\ o)\n poih/se&shy;<!-- ref: 54,6 --><lb/>
tai ou)d' e)k tou= mh\ o)/ntos, a)lla\ kata\ metaqe/seis e)n polloi=s, <!-- ref: 54,7 --><lb/>
tinw=n de\ kai\ proso/dous kai\ a)fo/dous. </s><s>o(/qen a)nagkai=on ta\ [mh\] <!-- ref: 54,8 --><lb/>
metatiqe/mena a)/fqarta ei)=nai kai\ th\n tou= metaba/llontos fu/sin <!-- ref: 54,9 --><lb/>
ou)k e)/xonta, o)/gkous de\ kai\ sxhmatismou\s i)di/ous: tau=ta ga\r <!-- ref: 54,10 --><lb/>
kai\ a)nagkai=on u(pome/nein. </s><s><!-- ref: 54,11 --><lb/>
kai\ ga\r e)n toi=s par' h(mi=n metasxh&shy;<!-- ref: 55,1 --><lb/>
matizome/nois kata\ th\n periai/resin to\ sxh=ma e)nupa/rxon lamba/&shy;<!-- ref: 55,2 --><lb/>
netai, ai( de\ poio/thtes ou)k e)nupa/rxousai e)n tw=| metaba/llonti, <!-- ref: 55,3 --><lb/>
w(/sper e)kei=no katalei/petai, a)ll' e)c o(/lou tou= sw/matos a)pollu/&shy;<!-- ref: 55,4 --><lb/>
menai. </s><s>i(kana\ ou)=n ta\ u(poleipo/mena tau=ta ta\s tw=n sugkri/sewn <!-- ref: 55,5 --><lb/>
diafora\s poiei=n, e)peidh/ per u(polei/pesqai/ ge/ tina a)nagkai=on kai\ <!-- ref: 55,6 --><lb/>
&lt;mh\&gt; ei)s to\ mh\ o)\n fqei/resqai. <!-- ref: 55,7 --><lb/>
</s></p><p><s>*(alla\ mh\n ou)de\ dei= nomi/zein pa=n me/geqos e)n tai=s a)to/mois <!-- ref: 55,8 --><lb/>
u(pa/rxein, i(/na mh\ ta\ faino/mena a)ntimarturh=|: parallaga\s de/ ti&shy;<!-- ref: 55,9 --><lb/>
nas megeqw=n nomiste/on ei)=nai. </s><s>be/ltion ga\r kai\ tou/tou proso/ntos <!-- ref: 55,10 --><lb/>
ta\ kata\ ta\ pa/qh kai\ ta\s <pb pagenum="244"/>ai)sqh/seis gino/mena a)podoqh/setai. </s><s><!-- ref: 55,11 --><lb/>
pa=n de\ me/geqos u(pa/rxon ou)/te xrh/simo/n e)sti pro\s ta\s tw=n poio&shy;<!-- ref: 56,1 --><lb/>
th/twn diafora/s, a)fi=xqai/ te a(/m' e)/dei kai\ pro\s h(ma=s o(rata\s <!-- ref: 56,2 --><lb/>
a)to/mous: o(\ ou) qewrei=tai gino/menon ou)/q' o(/pws a)\n ge/noito o(rath\ <!-- ref: 56,3 --><lb/>
a)/tomos e)/stin e)pinoh=sai. </s><s>*pro\s de\ tou/tois ou) dei= nomi/zein e)n tw=| <!-- ref: 56,4 --><lb/>
w(risme/nw| sw/mati a)pei/rous o)/gkous ei)=nai ou)d' o(phli/kous ou)=n. </s><s><!-- ref: 56,5 --><lb/>
w(/ste ou) mo/non th\n ei)s a)/peiron tomh\n e)pi\ tou)/latton a)nairete/on, <!-- ref: 56,6 --><lb/>
i(/na mh\ pa/nta a)sqenh= poiw=men ka)n tai=s perilh/yesi tw=n a)qro/wn  <!-- ref: 56,7 --><lb/>
ei)s to\ mh\ o)\n a)nagkazw/meqa ta\ o)/nta qli/bontes katanali/skein, <!-- ref: 56,8 --><lb/>
a)lla\ kai\ th\n meta/basin mh\ nomiste/on gi/nesqai e)n toi=s w(risme/&shy;<!-- ref: 56,9 --><lb/>
nois ei)s a)/peiron mhd' e)&lt;pi\&gt; tou)/latton. </s><s><!-- ref: 56,10 --><lb/>
ou)/te ga\r o(/pws, e)pei&shy;<!-- ref: 57,1 --><lb/>
da\n a(/pac tis ei)/ph| o(/ti a)/peiroi o)/gkoi e)/n tini u(pa/rxousin h)\ o(ph&shy;<!-- ref: 57,2 --><lb/>
li/koi ou)=n, e)/sti noh=sai: pw=s t' a)\n e)/ti tou=to peperasme/non ei)/h <!-- ref: 57,3 --><lb/>
to\ me/geqos; </s><s>phli/koi ga/r tines dh=lon w(s oi( a)/peiroi/ ei)sin o)/gkoi: <!-- ref: 57,4 --><lb/>
kai\ ou(=toi o(phli/koi a)/n pote w)=sin, a)/peiron a)\n h)=n kai\ to\ me/ge&shy;<!-- ref: 57,5 --><lb/>
qos. </s><s>a)/kron te e)/xontos tou= peperasme/nou dialhpto/n, ei) mh\ <!-- ref: 57,6 --><lb/>
kai\ kaq' e(auto\ qewrhto/n, ou)k e)/sti mh\ ou) kai\ to\ e(ch=s tou/&shy;<!-- ref: 57,7 --><lb/>
tou toiou=ton noei=n, kai\ ou(/tw kata\ to\ e(ch=s ei)s tou)/mprosqen <!-- ref: 57,8 --><lb/>
badi/zonta ei)s to\ a)/peiron u(pa/rxein kata\ &lt;to\&gt; toiou=ton a)fiknei=&shy;<!-- ref: 57,9 --><lb/>
sqai th=| e)nnoi/a|. </s><s><!-- ref: 57,10 --><lb/>
to/ te e)la/xiston to\ e)n th=| ai)sqh/sei dei= kata&shy;<!-- ref: 58,1 --><lb/>
noei=n o(/ti ou)/te toiou=to/n e)stin oi(=on to\ ta\s metaba/seis e)/xon ou)/te <!-- ref: 58,2 --><lb/>
pa/nth| pa/ntws a)no/moion, a)ll' e)/xon me/n tina koino/thta tw=n me&shy;<!-- ref: 58,3 --><lb/>
tabatw=n, dia/lhyin de\ merw=n ou)k e)/xon: a)ll' o(/tan dia\ th\n th=s <!-- ref: 58,4 --><lb/>
<pb pagenum="245"/>
koino/thtos prosemfe/reian oi)hqw=men dialh/yesqai/ ti au)tou=, to\ <!-- ref: 58,5 --><lb/>
me\n e)pita/de, to\ de\ e)pe/keina, to\ i)/son h(mi=n dei= prospi/ptein. </s><s>e(ch=s <!-- ref: 58,6 --><lb/>
te qewrou=men tau=ta a)po\ tou= prw/tou katarxo/menoi kai\ ou)k e)n <!-- ref: 58,7 --><lb/>
tw=| au)tw=|, ou)de\ me/resi merw=n a(pto/mena, a)ll' h)\ e)n th=| i)dio/thti <!-- ref: 58,8 --><lb/>
th=| e(autw=n ta\ mege/qh katametrou=nta, ta\ plei=w plei=on kai\ <!-- ref: 58,9 --><lb/>
ta\ e)la/ttw e)/latton. </s><s>tau/th| th=| a)nalogi/a| nomiste/on kai\ to\ e)n th=| <!-- ref: 58,10 --><lb/>
a)to/mw| e)la/xiston kexrh=sqai: <!-- ref: 58,11 --><lb/>
mikro/thti ga\r e)kei=no dh=lon w(s <!-- ref: 59,1 --><lb/>
diafe/rei tou= kata\ th\n ai)/sqhsin qewroume/nou, a)nalogi/a| de\ th=| <!-- ref: 59,2 --><lb/>
au)th=| ke/xrhtai. </s><s>e)pei\ per kai\ o(/ti me/geqos e)/xei h( a)/tomos, kata\ <!-- ref: 59,3 --><lb/>
th\n e)ntau=qa a)nalogi/an kathgorh/samen, mikro/n ti mo/non makra\n  <!-- ref: 59,4 --><lb/>
e)kbalo/ntes. </s><s>e)/ti te ta\ e)la/xista kai\ a)merh= pe/rata dei= nomi/zein <!-- ref: 59,5 --><lb/>
tw=n mhkw=n to\ katame/trhma e)c au(tw=n prw=ton toi=s mei/zosi kai\ <!-- ref: 59,6 --><lb/>
e)la/ttosi paraskeua/zonta th=| dia\ lo/gou qewri/a| e)pi\ tw=n a)ora/twn. </s><s><!-- ref: 59,7 --><lb/>
h( ga\r koino/ths h( u(pa/rxousa au)toi=s pro\s ta\ a)meta/bata i(kanh\ <!-- ref: 59,8 --><lb/>
to\ me/xri tou/tou suntele/sai, sumfo/rhsin de\ e)k tou/twn ki/nhsin <!-- ref: 59,9 --><lb/>
e)xo/ntwn ou)x oi(=o/n te gi/nesqai. <!-- ref: 59,10 --><lb/>
</s></p><p><s>*kai\ mh\n kai\ tou= a)pei/rou w(s me\n a)nwta/tw h)\ katwta/tw ou) <!-- ref: 60,1 --><lb/>
dei= kathgorei=n to\ a)/nw h)\ ka/tw. </s><s>i)/smen me/ntoi to\ u(pe\r kefalh=s, <!-- ref: 60,2 --><lb/>
o(/qen a)\n stw=men, ei)s a)/peiron a)/gein o)/n, mhde/pote fanei=sqai tou=to <!-- ref: 60,3 --><lb/>
h(mi=n, h)\ to\ u(poka/tw tou= nohqe/ntos ei)s a)/peiron, a(/ma a)/nw te ei)=nai <!-- ref: 60,4 --><lb/>
kai\ ka/tw pro\s to\ au)to/: tou=to ga\r a)du/naton dianohqh=nai. </s><s>w(/ste <!-- ref: 60,5 --><lb/>
e)/sti mi/an labei=n fora\n th\n a)/nw nooume/nhn ei)s a)/peiron kai\ mi/an <!-- ref: 60,6 --><lb/>
th\n ka/tw, a)\n kai\ muria/kis <pb pagenum="246"/>pro\s tou\s po/das tw=n e)pa/nw to\ par' <!-- ref: 60,7 --><lb/>
h(mw=n fero/menon &lt;ei)&gt; tou\s u(pe\r kefalh=s h(mw=n to/pous a)fiknh=&shy;<!-- ref: 60,8 --><lb/>
tai h)\ e)pi\ th\n kefalh\n tw=n u(poka/tw to\ par' h(mw=n ka/tw fe&shy;<!-- ref: 60,9 --><lb/>
ro/menon: h( ga\r o(/lh fora\ ou)qe\n h(=tton e(kate/ra e(kate/ra| a)nti&shy;<!-- ref: 60,10 --><lb/>
keime/nh e)p' a)/peiron noei=tai. <!-- ref: 60,11 --><lb/>
</s></p><p><s>*kai\ mh\n kai\ i)sotaxei=s a)nagkai=on ta\s a)to/mous ei)=nai, o(/tan <!-- ref: 61,1 --><lb/>
dia\ tou= kenou= ei)sfe/rwntai mhqeno\s a)ntiko/ptontos: ou)/te ga\r <!-- ref: 61,2 --><lb/>
ta\ bare/a qa=tton oi)sqh/setai tw=n mikrw=n kai\ kou/fwn, o(/tan ge <!-- ref: 61,3 --><lb/>
dh\ mhde\n a)panta=| au)toi=s: ou)/te ta\ mikra\ tw=n mega/lwn, pa/nta <!-- ref: 61,4 --><lb/>
po/ron su/mmetron e)/xonta, o(/tan mhqe\n mhde\ e)kei/nois a)ntiko/pth|: <!-- ref: 61,5 --><lb/>
ou)/q' h( a)/nw ou)/q' h( ei)s to\ pla/gion dia\ tw=n krou/sewn fora/, ou)/q' h(  <!-- ref: 61,6 --><lb/>
ka/tw dia\ tw=n i)di/wn barw=n. </s><s>e)f' o(po/son ga\r a)\n kati/sxh| e(ka/teron, <!-- ref: 61,7 --><lb/>
e)pi\ tosou=ton a(/ma noh/mati th\n fora\n sxh/sei, e(/ws a)ntiko/yh| h)\ <!-- ref: 61,8 --><lb/>
e)/cwqen h)\ e)k tou= i)di/ou ba/rous pro\s th\n tou= plh/cantos du/namin. <!-- ref: 61,9 --><lb/>
</s></p><p><s>*)alla\ mh\n kai\ kata\ ta\s sugkri/seis qa/ttwn e(te/ra e(te/ras <!-- ref: 62,1 --><lb/>
r(hqh/setai, tw=n a)to/mwn i)sotaxw=n ou)swn, tw=| e)f' e(/na to/pon fe/&shy;<!-- ref: 62,2 --><lb/>
resqai ta\s e)n toi=s a)qroi/smasin a)to/mous kai\ kata\ to\n e)la/xiston <!-- ref: 62,3 --><lb/>
sunexh= xro/non, ei) mh\ e)f' e(/na kata\ tou\s lo/gw| qewrhtou\s xro/&shy;<!-- ref: 62,4 --><lb/>
nous: a)lla\ pukno\n a)ntiko/ptousin, e(/ws a)\n u(po\ th\n ai)/sqhsin to\ <!-- ref: 62,5 --><lb/>
sunexe\s th=s fora=s gi/nhtai. </s><s>to\ ga\r prosdocazo/menon peri\ tou= <!-- ref: 62,6 --><lb/>
a)ora/tou, w(s a)/ra kai\ oi( dia\ lo/gou qewrhtoi\ xro/noi to\ sunexe\s <!-- ref: 62,7 --><lb/>
th=s fora=s e(/cousin, ou)k a)lhqe/s e)stin e)pi\ tw=n toiou/twn: e)pei\ to/ <!-- ref: 62,8 --><lb/>
ge qewrou/menon pa=n h)\ kat' e)pibolh\n lambano/menon th=| dianoi/a| <!-- ref: 62,9 --><lb/>
a)lhqe/s e)sti. <!-- ref: 62,10 --><lb/>
</s></p><p><s>*meta\ de\ tau=ta dei= sunora=n <pb pagenum="247"/>a)nafe/ronta e)pi\ ta\s ai)sqh/seis <!-- ref: 63,1 --><lb/>
kai\ ta\ pa/qh_ou(/tw ga\r h( bebaiota/th pi/stis e)/stai_o(/ti h( <!-- ref: 63,2 --><lb/>
yuxh\ sw=ma/ e)sti leptomere/s, par' o(/lon to\ a)/qroisma parespar&shy;<!-- ref: 63,3 --><lb/>
me/non, prosemfere/staton de\ pneu/mati, qermou= tina kra=sin <!-- ref: 63,4 --><lb/>
e)/xonti kai\ ph=| me\n tou/tw| prosemfere/s, ph=| de\ tou/tw|. </s><s>e)/sti de/ <!-- ref: 63,5 --><lb/>
ti me/ros pollh\n parallagh\n ei)lhfo\s th=| leptomerei/a| kai\ au)&shy;<!-- ref: 63,6 --><lb/>
tw=n tou/twn, sumpaqe\s dia\ tou=to ma=llon kai\ tw=| loipw=| a)qroi/&shy;<!-- ref: 63,7 --><lb/>
smati: tou=to de\ pa=n ai( duna/meis th=s yuxh=s dhlou=si kai\ ta\ <!-- ref: 63,8 --><lb/>
pa/qh kai\ ai( eu)kinhsi/ai kai\ ai( dianoh/seis kai\ w(=n stero/menoi <!-- ref: 63,9 --><lb/>
qnh/|skomen. </s><s>*kai\ mh\n kai\ o(/ti e)/xei h( yuxh\ th=s ai)sqh/sews th\n <!-- ref: 63,10 --><lb/>
plei/sthn ai)ti/an dei= kate/xein: <!-- ref: 63,11 --><lb/>
ou) mh\n ei)lh/fei a)\n tau/thn, ei) <!-- ref: 64,1 --><lb/>
mh\ u(po\ tou= loipou= a)qroi/smatos e)stega/zeto/ pws: to\ de\ loipo\n <!-- ref: 64,2 --><lb/>
a)/qroisma paraskeua/san e)kei/nh| th\n ai)ti/an tau/thn metei/lhfe  <!-- ref: 64,3 --><lb/>
kai\ au)to\ toiou/tou sumptw/matos par' e)kei/nhs, ou) me/ntoi pa/n&shy;<!-- ref: 64,4 --><lb/>
twn w(=n e)kei/nh ke/kthtai: dio\ a)pallagei/shs th=s yuxh=s ou)k e)/xei <!-- ref: 64,5 --><lb/>
th\n ai)/sqhsin. </s><s>ou) ga\r au)to\ e)n e(autw=| tau/thn e)ke/kthto th\n du/&shy;<!-- ref: 64,6 --><lb/>
namin, a)ll' e(te/rw| a(/ma suggegenhme/nw| au)tw=| pareskeu/azen, o(\ <!-- ref: 64,7 --><lb/>
dia\ th=s suntelesqei/shs peri\ au)to\ duna/mews kata\ th\n ki/nhsin <!-- ref: 64,8 --><lb/>
su/mptwma ai)sqhtiko\n eu)qu\s a)potelou=n e(autw= a)pedi/dou kata\ <!-- ref: 64,9 --><lb/>
th\n o(mou/rhsin kai\ sumpa/qeian kai\ e)kei/nw|, kaqa/per ei)=pon. </s><s><!-- ref: 64,10 --><lb/>
*dio\ dh\ kai\ e)nupa/rxousa h( yuxh\ ou)de/pote a)/llou tino\s me/rous <!-- ref: 65,1 --><lb/>
a)phllagme/nou a)naisqhtei=: a)ll' a(\ a)\n kai\ tau/ths cunapo/lhtai <!-- ref: 65,2 --><lb/>
tou= stega/zontos luqe/ntos <pb pagenum="248"/>ei)/q' o(/lou ei)/te kai\ me/rous tino/s, <!-- ref: 65,3 --><lb/>
e)a/n per diame/nh|, sw/|zei th\n ai)/sqhsin. </s><s>to\ de\ loipo\n a)/qroisma <!-- ref: 65,4 --><lb/>
diame/non kai\ o(/lon kai\ kata\ me/ros ou)k e)/xei th\n ai)/sqhsin e)kei/nou <!-- ref: 65,5 --><lb/>
a)phllagme/nou, o(/son pote/ e)sti to\ suntei=non tw=n a)to/mwn plh=qos <!-- ref: 65,6 --><lb/>
ei)s th\n th=s yuxh=s fu/sin. </s><s>*kai\ mh\n kai\ luome/nou tou= o(/lou a)qroi/&shy;<!-- ref: 65,7 --><lb/>
smatos h( yuxh\ diaspei/retai kai\ ou)ke/ti e)/xei ta\s au)ta\s duna/meis <!-- ref: 65,8 --><lb/>
ou)de\ kinei=tai, w(/ste ou)d' ai)/sqhsin ke/kthtai. </s><s><!-- ref: 65,9 --><lb/>
ou) ga\r oi(=o/n te <!-- ref: 66,1 --><lb/>
noei=n au)to\ ai)sqano/menon mh\ e)n tou/tw| tw=| susth/mati kai\ tai=s <!-- ref: 66,2 --><lb/>
kinh/sesi tau/tais xrw/menon, o(/tan ta\ stega/zonta kai\ perie/xonta <!-- ref: 66,3 --><lb/>
mh\ toiau=ta h)=|, e)n oi(=s nu=n ou)=sa e)/xei tau/tas ta\s kinh/seis. </s><s>*)alla\ <!-- ref: 66,4 --><lb/>
mh\n kai\ to/de &lpar;le/gei e)n a)/llois kai\ e)c a)to/mwn au)th\n <!-- ref: 66,5 --><lb/>
sugkei=sqai leiota/twn kai\ stroggulwta/twn, pollw=| tini diafe&shy;<!-- ref: 66,6 --><lb/>
rousw=n tw=n tou= puro/s: kai\ to\ me/n ti a)/logon au)th=s, o(\ tw=| loipw=| <!-- ref: 66,7 --><lb/>
parespa/rqai sw/mati: to\ de\ logiko\n e)n tw=| qw/raki, w(s dh=lon <!-- ref: 66,8 --><lb/>
e)/k te tw=n fo/bwn kai\ th=s xara=s: u(/pnon te gi/nesqai tw=n th=s  <!-- ref: 66,9 --><lb/>
yuxh=s merw=n tw=n par' o(/lhn th\n su/gkrisin paresparme/nwn e)g&shy;<!-- ref: 66,10 --><lb/>
katexome/nwn h)\ diaforoume/nwn, ei)/t' e)kpipto/ntwn toi=s e)perei&shy;<!-- ref: 66,11 --><lb/>
smoi=s. </s><s>to/ te spe/rma a)f' o(/lwn tw=n swma/twn fe/resqai.&rpar; <!-- ref: 66,12 --><lb/>
ge dei= <!-- ref: 67,1 --><lb/>
proskatanoei=n, o(/ti to\ a)sw/maton le/gomen kata\ th\n plei/sthn <!-- ref: 67,2 --><lb/>
o(mili/an tou= o)no/matos e)pi\ tou= kaq' e(auto\ nohqe/ntos a)/n: kaq' <!-- ref: 67,3 --><lb/>
e(auto\ de\ ou)k e)/sti noh=sai to\ a)sw/maton plh\n tou= kenou=: to\ de\ <!-- ref: 67,4 --><lb/>
keno\n ou)/te poih=sai ou)/te paqei=n du/natai, a)lla\ ki/nhsin mo/non di' <!-- ref: 67,5 --><lb/>
e(autou= toi=s sw/masi pare/xetai. </s><s>w(/sq' oi( le/gontes a)sw/maton <!-- ref: 67,6 --><lb/>
ei)=nai th\n yuxh\n mataii/+zousin. </s><s>ou)qe\n ga\r a)\n e)du/nato poiei=n ou)/te <!-- ref: 67,7 --><lb/>
pa/sxein, ei) h)=n toiau/th: nu=n d' e)nargw=s a)mfo/tera tau=ta <pb pagenum="249"/>dialam&shy;<!-- ref: 67,8 --><lb/>
ba/nomen peri\ th\n yuxh\n ta\ sumptw/mata. </s><s><!-- ref: 67,9 --><lb/>
tau=ta ou)=n pa/nta ta\ <!-- ref: 68,1 --><lb/>
dialogi/smata &lt;ta\&gt; peri\ yuxh=s a)na/gwn tis e)pi\ ta\ pa/qh kai\ ta\s <!-- ref: 68,2 --><lb/>
ai)sqh/seis, mnhmoneu/wn tw=n e)n a)rxh=| r(hqe/ntwn, i(kanw=s kato/ye&shy;<!-- ref: 68,3 --><lb/>
tai toi=s tu/pois e)mperieilhmme/na ei)s to\ kata\ me/ros a)po\ tou/twn <!-- ref: 68,4 --><lb/>
e)cakribou=sqai bebai/ws. <!-- ref: 68,5 --><lb/>
</s></p><p><s>*)alla\ mh\n kai\ ta\ sxh/mata kai\ ta\ xrw/mata kai\ ta\ mege/qh <!-- ref: 68,6 --><lb/>
kai\ ta\ ba/rh kai\ o(/sa a)/lla kathgorei=tai sw/matos w(s a)\n a)ei\ <!-- ref: 68,7 --><lb/>
sumbebhko/ta h)\ pa=sin h)\ toi=s o(ratoi=s kai\ kata\ th\n ai)/sqhsin <!-- ref: 68,8 --><lb/>
au)tw=n gnwstoi=s, ou)/q' w(s kaq' e(auta/s ei)si fu/seis docaste/on <!-- ref: 68,9 --><lb/>
_ou) ga\r dunato\n e)pinoh=sai tou=to_ <!-- ref: 68,10 --><lb/>
ou)/te o(/lws w(s ou)k ei)si/n, <!-- ref: 69,1 --><lb/>
ou)/q' w(s e(/ter' a)/tta prosupa/rxonta tou/tw| a)sw/mata, ou)/q' w(s <!-- ref: 69,2 --><lb/>
mo/ria tou/tou, a)ll' w(s to\ o(/lon sw=ma kaqo/lou e)k tou/twn pa/n&shy;<!-- ref: 69,3 --><lb/>
twn th\n e(autou= fu/sin e)/xon a)i/dion, ou)x oi(=on de\ ei)=nai sumpeforh&shy;<!-- ref: 69,4 --><lb/>
me/non_w(/sper o(/tan e)c au)tw=n tw=n o)/gkwn mei=zon a)/qroisma  <!-- ref: 69,5 --><lb/>
susth=| h)/toi tw=n prw/twn h)\ tw=n tou= o(/lou megeqw=n tou=de tino\s <!-- ref: 69,6 --><lb/>
e)latto/nwn_a)lla\ mo/non, w(s le/gw, e)k tou/twn a(pa/ntwn th\n <!-- ref: 69,7 --><lb/>
e(autou= fu/sin e)/xon a)i/dion. </s><s>kai\ e)pibola\s me\n e)/xonta i)di/as pa/nta <!-- ref: 69,8 --><lb/>
tau=ta/ e)sti kai\ dialh/yeis, sumparakolouqou=ntos de\ tou= a)qro/ou <!-- ref: 69,9 --><lb/>
kai\ ou)qamh=| a)posxizome/nou, a)lla\ kata\ th\n a)qro/an e)/nnoian tou= <!-- ref: 69,10 --><lb/>
sw/matos kathgori/an ei)lhfo/tos. <!-- ref: 69,11 --><lb/>
</s></p><p><s>*kai\ mh\n kai\ toi=s sw/masi sumpi/ptei polla/kis kai\ ou)k a)i/&shy;<!-- ref: 70,1 --><lb/>
dion parakolouqei=n ou)/t' e)n toi=s a)ora/tois kai\ ou)/te a)sw/mata. </s><s><!-- ref: 70,2 --><lb/>
w(/ste dh\ kata\ th\n plei/sthn fora\n tou/tw| tw=| o)no/mati xrw/me&shy;<!-- ref: 70,3 --><lb/>
noi fanera\ poiou=men ta\ sumptw/mata ou)/te th\n tou= o(/lou fu/sin <pb pagenum="250"/><!-- ref: 70,4 --><lb/>
e)/xein, o(\ sullabo/ntes kata\ to\ a)qro/on sw=ma prosagoreu/omen, <!-- ref: 70,5 --><lb/>
ou)/te th\n tw=n a)i/dion parakolouqou/ntwn, w(=n a)/neu sw=ma ou) du&shy;<!-- ref: 70,6 --><lb/>
nato\n noei=sqai. </s><s>kat' e)pibola\s d' a)/n tinas parakoluqou=ntos <!-- ref: 70,7 --><lb/>
tou= a)qro/ou e(/kasta prosagoreuqei/h, <!-- ref: 70,8 --><lb/>
a)ll' o(/te dh/pote e(/ka&shy;<!-- ref: 71,1 --><lb/>
sta sumbai/nonta qewrei=tai, ou)k a)i/dion tw=n sumptw/matwn pa&shy;<!-- ref: 71,2 --><lb/>
rakolouqou/ntwn. </s><s>kai\ ou)k e)celate/on e)k tou= o)/ntos tau/thn th\n <!-- ref: 71,3 --><lb/>
e)na/rgeian, o(/ti ou)k e)/xei th\n tou= o(/lou fu/sin w(=| sumbai/nei o(\ dh\ <!-- ref: 71,4 --><lb/>
kai\ sw=ma prosagoreu/omen, ou)de\ th\n tw=n a)i/dion parakolou&shy;<!-- ref: 71,5 --><lb/>
qou/ntwn, ou)d' au)= kaq' au(ta\ nomiste/on_ou)de\ ga\r tou=to dia&shy;<!-- ref: 71,6 --><lb/>
nohto\n ou)/t' e)pi\ tou/twn ou)/t' e)pi\ tw=n a)i/dion sumbebhko/twn_a)ll' <!-- ref: 71,7 --><lb/>
o(/per kai\ fai/netai, sumptw/mata pa/nta ta\ toiau=ta nomiste/on, <!-- ref: 71,8 --><lb/>
kai\ ou)k a)i/dion parakolouqou=nta ou)d' au)= fu/sews kaq' e(auta\ <!-- ref: 71,9 --><lb/>
ta/gma e)/xonta, a)ll' o(\n tro/pon au)th\ h( ai)/sqhsis th\n i)dio/thta <!-- ref: 71,10 --><lb/>
poiei=, qewrei=tai. <!-- ref: 71,11 --><lb/>
</s></p><p><s>*kai\ mh\n kai\ to/de ge dei= proskatanoh=sai sfodrw=s: to\n ga\r <!-- ref: 72,1 --><lb/>
dh\ xro/non ou) zhthte/on w(/sper kai\ ta\ loipa/, o(/sa e)n u(pokeime/nw| <!-- ref: 72,2 --><lb/>
zhtou=men a)na/gontes e)pi\ ta\s blepome/nas par' h(mi=n au)toi=s pro- <!-- ref: 72,3 --><lb/>
lh/yeis, a)ll' au)to\ to\ e)na/rghma, kaq' o(\ to\n polu\n h)\ o)li/gon <!-- ref: 72,4 --><lb/>
xro/non a)nafwnou=men, suggenikw=s tou=to perife/rontes, a)nalo&shy;<!-- ref: 72,5 --><lb/>
giste/on. </s><s>kai\ ou)/te diale/ktous w(s belti/ous metalhpte/on, a)ll' <!-- ref: 72,6 --><lb/>
au)tai=s tai=s u(parxou/sais kat' au)tou= xrhste/on, ou)/te a)/llo ti <!-- ref: 72,7 --><lb/>
kat' au)tou= kathgorhte/on, w(s th\n au)th\n ou)si/an e)/xontos tw=| <!-- ref: 72,8 --><lb/>
i)diw/mati tou/tw|_kai\ ga\r tou=to poiou=si/ tines_a)lla\ mo/non <!-- ref: 72,9 --><lb/>
w(=| sumple/komen to\ i)/dion tou=to kai\ parametrou=<pb pagenum="251"/>men, ma/lista <!-- ref: 72,10 --><lb/>
e)pilogi/ste/on. <!-- ref: 72,11 --><lb/>
kai\ ga\r tou=to ou)k a)podei/cews prosdei=tai a)ll' <!-- ref: 73,1 --><lb/>
e)pilogismou=, o(/ti tai=s h(me/rais kai\ tai=s nuci\ sumple/komen, kai\ <!-- ref: 73,2 --><lb/>
toi=s tou/twn me/resin, w(sau/tws de\ kai\ toi=s pa/qesi kai\ tai=s <!-- ref: 73,3 --><lb/>
a)paqei/ais, kai\ kinh/sesi kai\ sta/sesin i)/dio/n ti su/mptwma, peri\ <!-- ref: 73,4 --><lb/>
tau=ta pa/lin au)to\ tou=to e)nnoou=ntes, kaqo\ xro/non o)noma/zomen <!-- ref: 73,5 --><lb/>
&lpar;fhsi\ de\ tou=to kai\ e)n th=| % deute/ra| % *peri\ fu/sews kai\ <!-- ref: 73,6 --><lb/>
e)n th=| *mega/lh| e)pitomh=|.&rpar; <!-- ref: 73,7 --><lb/>
</s></p><p><s>*)epi/ te toi=s proeirhme/nois tou\s ko/smous dei= kai\ pa=san su/g&shy;<!-- ref: 73,8 --><lb/>
krisin peperasme/nhn to\ o(moeide\s toi=s qewroume/nois puknw=s <!-- ref: 73,9 --><lb/>
e)/xousan nomi/zein gegone/nai a)po\ tou= a)pei/rou, pa/ntwn tou/twn <!-- ref: 73,10 --><lb/>
e)k sustrofw=n i)di/wn a)pokekrime/nwn kai\ meizo/nwn kai\ e)latto/&shy;<!-- ref: 73,11 --><lb/>
nwn: kai\ pa/lin dialu/esqai pa/nta, ta\ me\n qa=tton, ta\ de\ bra&shy;<!-- ref: 73,12 --><lb/>
du/teron, kai\ ta\ me\n u(po\ tw=n toiw=nde, ta\ de\ u(po\ tw=n toiw=nde <!-- ref: 73,13 --><lb/>
tou=to pa/sxonta. </s><s><!-- ref: 73,14 --><lb/>
&lpar;dh=lon ou)=n w(s kai\ fqartou/s fhsi <!-- ref: 74,1 --><lb/>
tou\s ko/smous, metaballo/ntwn tw=n merw=n. </s><s>kai\ e)n a)/llois th\n gh=n <!-- ref: 74,2 --><lb/>
tw=| a)e/ri e)poxei=sqai.&rpar; *)/eti de\ tou\s ko/smous ou)/te e)c a)na/gkhs dei= <!-- ref: 74,3 --><lb/>
nomi/zein e(/na sxhmatismo\n e)/xontas, a)lla\ &lpar;kai\ diafo/rous au)tou\s <!-- ref: 74,4 --><lb/>
e)n th=| &lt;i&gt; </s><s>&lt;b&gt; </s><s>*peri\ fu/sew/s fhsin&rpar; ou(\s me\n ga\r sfairoei- <!-- ref: 74,5 --><lb/>
dei=s, kai\ w)|oeidei=s a)/llous, kai\ a)lloiosxh/monas e(te/rous: ou) me/n&shy;<!-- ref: 74,6 --><lb/>
toi pa=n sxh=ma e)/xein: ou)de\ zw=|a ei)=nai a)pokriqe/nta a)po\ tou= a)pei/&shy;<!-- ref: 74,7 --><lb/>
rou. </s><s>ou)de\ ga\r a)\n a)podei/ceien ou)dei/s, w(s &lt;e)n&gt; me\n tw=| toiou/tw| <!-- ref: 74,8 --><lb/>
kai\ ou)k a)\n e)mperielh/fqh ta\ toiau=ta spe/rmata e)c w(=n zw=|a/ te <!-- ref: 74,9 --><lb/>
kai\ futa\ kai\ ta\ loipa\ pa/nta &lt;ta\&gt; qewrou/mena suni/statai, e)n <!-- ref: 74,10 --><lb/>
de\ tw=| toiou/tw| ou)k a)\n e)dunh/qh. </s><s>w(sau/tws de\ kai\ e)ntrafh=nai. </s><s><!-- ref: 74,11 --><lb/>
to\n au)<pb pagenum="252"/>to\n de\ tro/pon kai\ e)pi\ gh=s nomiste/on. <!-- ref: 74,12 --><lb/>
</s></p><p><s>*)alla\ mh\n u(polhpte/on kai\ th\n fu/sin polla\ kai\ pantoi=a <!-- ref: 75,1 --><lb/>
u(po\ au)tw=n tw=n pragma/twn didaxqh=nai/ te kai\ a)nagkasqh=nai, <!-- ref: 75,2 --><lb/>
to\n de\ logismo\n ta\ u(po\ tau/ths paregguhqe/nta u(/steron e)pa&shy;<!-- ref: 75,3 --><lb/>
kribou=n kai\ proseceuri/skein e)n me/n tisi qa=tton, e)n de/ tisi bra&shy;<!-- ref: 75,4 --><lb/>
du/teron kai\ e)n me/n tisi perio/dois kai\ xro/nois [a)po\ tw=n a)po\ <!-- ref: 75,5 --><lb/>
tou= a)pei/rou] ...... </s><s>e)n de/ tisi kat' e)la/ttous. </s><s>*(/oqen kai\ ta\ <!-- ref: 75,6 --><lb/>
o)no/mata e)c a)rxh=s mh\ qe/sei gene/sqai, a)ll' au)ta\s ta\s fu/seis <!-- ref: 75,7 --><lb/>
tw=n a)nqrw/pwn kaq' e(/kasta e)/qnh i)/dia pasxou/sas pa/qh kai\ <!-- ref: 75,8 --><lb/>
i)/dia lambanou/sas fanta/smata i)di/ws to\n a)e/ra e)kpe/mpein stel&shy;<!-- ref: 75,9 --><lb/>
lo/menon u(f' e(ka/stwn tw=n paqw=n kai\ tw=n fantasma/twn, w(s a)/n <!-- ref: 75,10 --><lb/>
pote kai\ h( para\ tou\s to/pous tw=n e)qnw=n diafora\ ei)/h: <!-- ref: 75,11 --><lb/>
u(/ste&shy;<!-- ref: 76,1 --><lb/>
ron de\ koinw=s kaq' e(/kasta e)/qnh ta\ i)/dia teqh=nai pro\s to\ ta\s <!-- ref: 76,2 --><lb/>
dhlw/seis h(=tton a)mfibo/lous gene/sqai a)llh/lois kai\ suntomwte/&shy;<!-- ref: 76,3 --><lb/>
rws dhloume/nas: tina\ de\ kai\ ou) sunorw/mena pra/gmata ei)sfe/&shy;<!-- ref: 76,4 --><lb/>
rontas tou\s suneido/tas paregguh=sai/ tinas fqo/ggous tou\s &lt;me\n&gt; <!-- ref: 76,5 --><lb/>
a)nagkasqe/ntas a)nafwnh=sai, tou\s de\ tw=| logismw=| e(lome/nous <!-- ref: 76,6 --><lb/>
kata\ th\n plei/sthn ai)ti/an ou(/tws e(rmhneu=sai. <!-- ref: 76,7 --><lb/>
</s></p><p><s>*kai\ mh\n e)n toi=s metew/rois fora\n kai\ troph\n kai\ e)/kleiyin <!-- ref: 76,8 --><lb/>
kai\ a)natolh\n kai\ du/sin kai\ ta\ su/stoixa tou/tois mh/te leitour&shy;<!-- ref: 76,9 --><lb/>
gou=nto/s tinos nomi/zein dei= gi/nesqai kai\ diata/ttontos h)\ diata/- <!-- ref: 76,10 --><lb/>
cantos kai\ a(/ma th\n pa=san makario/thta e)/xontos meta\ a)fqar&shy;<!-- ref: 76,11 --><lb/>
si/as <!-- ref: 76,12 --><lb/>
_ou) ga\r sumfwnou=si pragmatei=ai kai\ fronti/des kai\ <!-- ref: 77,1 --><lb/>
o)rgai\ kai\ xa/rites makario/thti, a)ll' e)n a)sqenei/a| kai\ fo/bw| kai\ <!-- ref: 77,2 --><lb/>
<pb pagenum="253"/>
prosdeh/sei tw=n plhsi/on tau=ta gi/netai_mh/te au)= pu=r a(/ma <!-- ref: 77,3 --><lb/>
o)/nta sunestramme/non th\n makario/thta kekthme/na kata\ bou/lh&shy;<!-- ref: 77,4 --><lb/>
sin ta\s kinh/seis tau/tas lamba/nein: a)lla\ pa=n to\ se/mnwma th&shy;<!-- ref: 77,5 --><lb/>
rei=n kata\ pa/nta o)no/mata fero/mena e)pi\ ta\s toiau/tas e)nnoi/as, <!-- ref: 77,6 --><lb/>
i(/na mhde\n u(penanti/on e)c au)tw=n tw=| semnw/mati do/ch|: ei) de\ mh/, <!-- ref: 77,7 --><lb/>
to\n me/giston ta/raxon e)n tai=s yuxai=s au)th\ h( u(penantio/ths pa&shy;<!-- ref: 77,8 --><lb/>
raskeua/sei. </s><s>o(/qen dh\ kata\ ta\s e)c a)rxh=s e)napolh/yeis tw=n su&shy;<!-- ref: 77,9 --><lb/>
strofw=n tou/twn e)n th=| tou= ko/smou gene/sei dei= doca/zein kai\ th\n <!-- ref: 77,10 --><lb/>
a)na/gkhn tau/thn kai\ peri/odon suntelei=sqai. <!-- ref: 77,11 --><lb/>
</s></p><p><s>*kai\ mh\n kai\ th\n u(pe\r tw=n kuriwta/twn ai)ti/an e)cakribw=sai <!-- ref: 78,1 --><lb/>
fusiologi/as e)/rgon ei)=nai dei= nomi/zein, kai\ to\ maka/rion e)n th=| peri\ <!-- ref: 78,2 --><lb/>
metew/rwn gnw/sei e)ntau=qa peptwke/nai kai\ e)n tw=| ti/nes fu/seis <!-- ref: 78,3 --><lb/>
ai( qewrou/menai kata\ ta\ mete/wra tauti/, kai\ o(/sa suggenh= pro\s <!-- ref: 78,4 --><lb/>
th\n ei)s tou=to a)kri/beian: e)/ti te ou) to\ pleonaxw=s e)n toi=s toiou/&shy;<!-- ref: 78,5 --><lb/>
tois ei)=nai kai\ to\ e)ndexo/menon kai\ a)/llws pws e)/xein, a)ll' a(plw=s <!-- ref: 78,6 --><lb/>
mh\ ei)=nai e)n a)fqa/rtw| kai\ makari/a| fu/sei tw=n dia/krisin u(pobal&shy;<!-- ref: 78,7 --><lb/>
lo/ntwn h)\ ta/raxon mhqe/n. </s><s>kai\ tou=to katalabei=n th=| dianoi/a| <!-- ref: 78,8 --><lb/>
e)/stin a(plw=s ei)=nai. </s><s><!-- ref: 78,9 --><lb/>
to\ d' e)n th=| i(stori/a| peptwko\s th=s du/sews <!-- ref: 79,1 --><lb/>
kai\ a)natolh=s kai\ troph=s kai\ e)klei/yews kai\ o(/sa suggenh= tou/&shy;<!-- ref: 79,2 --><lb/>
tois mhqe\n e)/ti pro\s to\ maka/rion th=s gnw/sews suntei/nein a)ll' <!-- ref: 79,3 --><lb/>
o(moi/ws tou\s fo/bous e)/xein tou\s tau=ta kateido/tas, ti/nes d' ai( <!-- ref: 79,4 --><lb/>
fu/seis a)gnoou=ntas kai\ ti/nes ai( kuriw/tatai ai)ti/ai, kai\ ei) mh\  <!-- ref: 79,5 --><lb/>
prosh/|desan tau=ta: <pb pagenum="254"/> xalepa\ kai\ plei=a, o(/tan to\ qa/mbos e)k th=s <!-- ref: 79,6 --><lb/>
tou/twn proskatanoh/sews mh\ du/nhtai th\n lu/sin lamba/nein kata\ <!-- ref: 79,7 --><lb/>
th\n peri\ tw=n kuriwta/twn oi)konomi/an. </s><s>dio\ dh\ kai\ plei/ous ai)ti/as <!-- ref: 79,8 --><lb/>
eu(ri/skomen tropw=n kai\ du/sewn kai\ a)natolw=n kai\ e)klei/yewn kai\ <!-- ref: 79,9 --><lb/>
tw=n toioutotro/pwn w(/sper kai\ e)n toi=s kata\ me/ros ginome/nois, <!-- ref: 79,10 --><lb/>
kai\ ou) dei= nomi/zein th\n u(pe\r tou/twn xrei/an a)kri/beian mh\ a)pei&shy;<!-- ref: 80,1 --><lb/>
lhfe/nai, o(/sh pro\s to\ a)ta/raxon kai\ maka/rion h(mw=n suntei/nei. </s><s><!-- ref: 80,2 --><lb/>
w(/ste paraqewrou=ntas posaxw=s par' h(mi=n to\ o(/moion gi/netai, <!-- ref: 80,3 --><lb/>
ai)tiologhte/on u(pe/r te tw=n metew/rwn kai\ panto\s tou= a)dh/lou, <!-- ref: 80,4 --><lb/>
katafronou=ntas tw=n ou)/te &lt;to\&gt; monaxw=s e)/xon h)\ gino/menon gnw&shy;<!-- ref: 80,5 --><lb/>
rizo/ntwn ou)/te to\ pleonaxw=s sumbai=non, &lt;e)pi\ tw=n&gt; th\n e)k tw=n <!-- ref: 80,6 --><lb/>
a)posthma/twn fantasi/an paradido/ntwn, e)/ti te a)gnoou=ntwn kai\ <!-- ref: 80,7 --><lb/>
e)n poi/ois ou)k e)/stin a)tarakth=sai &lt;kai\ e)n poi/ois o(moi/ws a)tara&shy;<!-- ref: 80,8 --><lb/>
kth=sai&gt;. </s><s>a)\n ou)=n oi)w/meqa kai\ w(di/ pws e)ndexo/menon au)to\ gi/ne&shy;<!-- ref: 80,9 --><lb/>
sqai [kai\ e)n poi/ois o(moi/ws a)tarakth=sai], au)to\ to\ o(/ti pleona&shy;<!-- ref: 80,10 --><lb/>
xw=s gi/netai gnwri/zontes, w(/sper ka)\n o(/ti w(di/ pws gi/netai ei)dw=&shy;<!-- ref: 80,11 --><lb/>
men, a)tarakth/somen. </s><s><!-- ref: 80,12 --><lb/>
*)epi\ de\ tou/tois o(/lws a(/pasin e)kei=no dei= <!-- ref: 81,1 --><lb/>
katanoei=n, o(/ti ta/raxos o( kuriw/tatos tai=s a)nqrwpi/nais yuxai=s <!-- ref: 81,2 --><lb/>
gi/netai e)n tw=| tau)ta\ maka/ria/ te doca/zein &lt;ei)=nai&gt; kai\ a)/fqarta <!-- ref: 81,3 --><lb/>
kai\ u(penanti/as e)/xein tou/tois a(/ma boulh/seis kai\ pra/ceis kai\ <!-- ref: 81,4 --><lb/>
ai)ti/as, kai\ e)n tw=| ai)w/nio/n ti deino\n h)\ prosdoka=n h)\ u(popteu/ein <!-- ref: 81,5 --><lb/>
kata\ tou\s mu/qous, ei)/te kai\ au)th\n th\n a)naisqhsi/an th\n e)n tw=| <!-- ref: 81,6 --><lb/>
teqna/nai foboume/nous w(/sper ou)=san kat' au)tou/s, kai\ e)n tw=| mh\ <!-- ref: 81,7 --><lb/>
do/cais tau=&shy;<pb pagenum="255"/>ta pa/sxein a)ll' a)lo/gw| ge/ tini parasta/sei, o(/qen mh\ <!-- ref: 81,8 --><lb/>
o(ri/zontas to\ deino\n th\n i)/shn h)\ kai\ e)pitetame/nhn taraxh\n lamba/- <!-- ref: 81,9 --><lb/>
nein tw=| ei) kai\ e)do/cazon tau=ta: <!-- ref: 81,10 --><lb/>
h( de\ a)taraci/a tw=| tou/twn pa/n&shy;<!-- ref: 82,1 --><lb/>
twn a)polelu/sqai kai\ sunexh= mnh/mhn e)/xein tw=n o(/lwn kai\ kuriw&shy;<!-- ref: 82,2 --><lb/>
ta/twn. </s><s>*(/oqen toi=s pa/qesi prosekte/on toi=s parou=si kai\ tai=s <!-- ref: 82,3 --><lb/>
ai)sqh/sesi, kata\ me\n to\ koino\n tai=s koinai=s, kata\ de\ to\ i)/dion <!-- ref: 82,4 --><lb/>
tai=s i)di/ais, kai\ pa/sh| th=| parou/sh| kaq' e(/kaston tw=n krithri/wn <!-- ref: 82,5 --><lb/>
e)nargei/a|: a)\n ga\r tou/tois prose/xwmen, to\ o(/qen o( ta/raxos kai\ <!-- ref: 82,6 --><lb/>
o( fo/bos e)gi/neto e)caitiologh/somen o)rqw=s kai\ a)polu/somen, u(pe\r <!-- ref: 82,7 --><lb/>
te metew/rwn ai)tiologou=ntes kai\ tw=n loipw=n tw=n a)ei\ parempi&shy;<!-- ref: 82,8 --><lb/>
pto/ntwn, o(/sa fobei= tou\s loipou\s e)sxa/tws. <!-- ref: 82,9 --><lb/>
</s></p><p><s>*tau=ta/ soi, w)= *(hro/dote, e)/sti kefalaiwde/stata u(pe\r th=s <!-- ref: 82,10 --><lb/>
tw=n o(/lwn fu/sews e)pitetmhme/na. </s><s><!-- ref: 82,11 --><lb/>
w(/st' a)\n ge/noito ou(=tos o( <!-- ref: 83,1 --><lb/>
lo/gos dunato/s, katasxeqei\s met' a)kribei/as, oi)=mai, e)a\n mh\ kai\ <!-- ref: 83,2 --><lb/>
pro\s a(/panta badi/sh| tis tw=n kata\ me/ros a)kribwma/twn, a)su/m&shy;<!-- ref: 83,3 --><lb/>
blhton au)to\n pro\s tou\s loipou\s a)nqrw/pous a(dro/thta lh/ye&shy;<!-- ref: 83,4 --><lb/>
sqai. </s><s>kai\ ga\r kai\ kaqara\ a)f' e(autou= poih/sei polla\ tw=n kata\ <!-- ref: 83,5 --><lb/>
me/ros e)cakriboume/nwn kata\ th\n o(/lhn pragmatei/an h(mi=n, kai\ <!-- ref: 83,6 --><lb/>
au)ta\ tau=ta e)n mnh/mh| tiqe/mena sunexw=s bohqh/sei. </s><s>toiau=ta ga/r <!-- ref: 83,7 --><lb/>
e)stin, w(/ste kai\ tou\s kata\ me/ros h)/dh e)cakribou=ntas i(kanw=s h)\ <!-- ref: 83,8 --><lb/>
kai\ telei/ws, ei)s ta\s toiau/tas a)nalu/ontas e)pibola\s ta\s plei/&shy;<!-- ref: 83,9 --><lb/>
stas tw=n periodeiw=n u(pe\r th=s o(/lhs fu/sews poiei=sqai: o(/soi de\ <!-- ref: 83,10 --><lb/>
mh\ pantelw=s au)tw=n tw=n a)potelou<pb pagenum="256"/>me/nwn ei)si/n, e)k tou/twn kai\ <!-- ref: 83,11 --><lb/>
kata\ to\n a)/neu fqo/ggwn tro/pon th\n a(/ma noh/mati peri/odon tw=n <!-- ref: 83,12 --><lb/>
kuriwta/twn pro\s galhnismo\n poiou=ntai.  <!-- ref: 83,13 --><lb/>
</s></p></chap>
<chap><p><s>CANONICA EPICURI <!-- ref:  --><lb/><foreign lang="la">[NOT TRANSCRIBED -- FROM SEXTUS EMPIRICUS]</foreign></s><pb pagenum="257"/></p></chap>
<chap>
<p type="head"><s>*)epi/kouros *puqoklei= xai/rein. <!-- ref: 84,t --><lb/>
</s></p><p><s>*)/hnegke/ moi *kle/wn e)pistolh\n para\ sou= e)n h(=| filofronou/&shy;<!-- ref: 84,1 --><lb/>
meno/s te peri\ h(ma=s diete/leis a)ci/ws th=s h(mete/ras peri\ seauto\n <!-- ref: 84,2 --><lb/>
spoudh=s, kai\ ou)k a)piqa/nws e)peirw= mnhmoneu/ein tw=n ei)s maka/&shy;<!-- ref: 84,3 --><lb/>
rion bi/on sunteino/ntwn dialogismw=n, e)de/ou te seautw=| peri\ tw=n <!-- ref: 84,4 --><lb/>
metew/rwn <pb pagenum="258"/>su/ntomon kai\ eu)peri/grafon dialogismo\n a)postei=lai, <!-- ref: 84,5 --><lb/>
i(/na r(a|di/ws mnhmoneu/h|s: ta\ ga\r e)n a)/llois h(mi=n gegramme/na <!-- ref: 84,6 --><lb/>
dusmnhmo/neuta ei)=nai, kai/toi, w(s e)/fhs, sunexw=s au)ta\ basta/zeis. </s><s><!-- ref: 84,7 --><lb/>
h(mei=s de\ h(de/ws te/ sou th\n de/hsin a)pedeca/meqa kai\ e)lpi/sin <!-- ref: 84,8 --><lb/>
h(dei/ais sunesxe/qhmen. </s><s><!-- ref: 84,9 --><lb/>
gra/yantes ou)=n ta\ loipa\ pa/nta sunte&shy;<!-- ref: 85,1 --><lb/>
lou=men a(/per h)ci/wsas polloi=s kai\ a)/llois e)so/mena xrh/sima ta\ <!-- ref: 85,2 --><lb/>
dialogi/smata tau=ta, kai\ ma/lista toi=s newsti\ fusiologi/as <!-- ref: 85,3 --><lb/>
gnhsi/ou geuome/nois kai\ toi=s ei)s a)sxoli/as baqute/ras, tw=n e)gku&shy;<!-- ref: 85,4 --><lb/>
kli/wn tino\s e)mpeplegme/nois. </s><s>kalw=s dh\ au)ta\ dia/labe, kai\ dia\ <!-- ref: 85,5 --><lb/>
mnh/mhs e)/xwn o)ce/ws au)ta\ perio/deue meta\ tw=n loipw=n w(=n e)n <!-- ref: 85,6 --><lb/>
th=| mikra=| e)pitomh=| pro\s *(hro/doton a)pestei/lamen. <!-- ref: 85,7 --><lb/>
</s></p><p><s>*prw=ton me\n ou)=n mh\ a)/llo ti te/los e)k th=s peri\ metew/rwn <!-- ref: 85,8 --><lb/>
gnw/sews ei)/te kata\ sunafh\n legome/nwn ei)/te au)totelw=s nomi/- <!-- ref: 85,9 --><lb/>
zein ei)=nai h)/per a)taraci/an kai\ pi/stin be/baion, kaqa/per kai\ e)pi\ <!-- ref: 85,10 --><lb/>
tw=n loipw=n: <!-- ref: 85,11 --><lb/>
mh/te to\ a)du/naton [kai\] parabia/zesqai, mh/te <!-- ref: 86,1 --><lb/>
o(moi/an kata\ pa/nta th\n qewri/an e)/xein h)\ toi=s peri\ bi/wn lo/gois <!-- ref: 86,2 --><lb/>
h)\ toi=s kata\ th\n tw=n a)/llwn fusikw=n problhma/twn ka/qarsin, <!-- ref: 86,3 --><lb/>
oi(=on o(/ti to\ pa=n sw=ma kai\ a)nafh\s fu/sis e)sti/n, h)\ o(/ti a)/toma stoi&shy;<!-- ref: 86,4 --><lb/>
xei=a kai\ pa/nta ta\ toiau=ta dh\ o(/sa monaxh\n e)/xei toi=s fainome/nois <!-- ref: 86,5 --><lb/>
sumfwni/an: o(/per e)pi\ tw=n metew/rwn ou)x u(pa/rxei, a)lla\ tau=ta/ <!-- ref: 86,6 --><lb/>
ge pleonaxh\n e)/xei kai\ th=s gene/sews ai)ti/an kai\ th=s ou)si/as <!-- ref: 86,7 --><lb/>
tai=s ai)sqh/sesi su/mfwnon kathgori/an. </s><s>ou) ga\r kata\ a)ciw/mata <!-- ref: 86,8 --><lb/>
kena\ kai\ nomoqesi/as fusiologhte/on, a)ll' w(s ta\ faino/mena e)k&shy;<!-- ref: 86,9 --><lb/>
kalei=tai: <!-- ref: 86,10 --><lb/>
ou) ga\r h)/dh a)logi/as kai\ kenh=s <pb pagenum="259"/>do/chs o( bi/os h(mw=n <!-- ref: 87,1 --><lb/>
e)/xei xrei/an, a)lla\ tou= a)qoru/bws h(ma=s zh=n. </s><s>pa/nta me\n ou)=n gi/&shy;<!-- ref: 87,2 --><lb/>
netai a)sei/stws kata\ pa/ntwn kata\ pleonaxo\n tro/pon e)kkaqai&shy;<!-- ref: 87,3 --><lb/>
rome/nwn sumfw/nws toi=s fainome/nois, o(/tan tis to\ piqanologou/&shy;<!-- ref: 87,4 --><lb/>
menon u(pe\r au)tw=n deo/ntws katali/ph|: o(/tan de/ tis to\ me\n a)po&shy;<!-- ref: 87,5 --><lb/>
li/ph| to\ de\ e)kba/lh| o(moi/ws su/mfwnon o)\n tw=| fainome/nw|, dh=lon <!-- ref: 87,6 --><lb/>
o(/ti kai\ e)k panto\s e)kpi/ptei fusiologh/matos, e)pi\ de\ to\n mu=qon <!-- ref: 87,7 --><lb/>
katarrei=. <!-- ref: 87,8 --><lb/>
</s></p><p><s>*shmei=a d' e)pi\ tw=n e)n toi=s metew/rois sunteloume/nwn fe/rei <!-- ref: 87,9 --><lb/>
tw=n par' h(mi=n tina fainome/nwn, a(\ qewrei=tai h(=| u(pa/rxei: kai\ ou) <!-- ref: 87,10 --><lb/>
ta\ e)n toi=s metw/rois faino/mena: tau=ta ga\r e)nde/xetai pleonaxw=s <!-- ref: 87,11 --><lb/>
gi/nesqai. </s><s><!-- ref: 87,12 --><lb/>
to\ me/ntoi fa/ntasma e(ka/stou thrhte/on kai\ e)pi\ ta\ <!-- ref: 88,1 --><lb/>
sunapto/mena tou/tw| diairete/on, a(\ ou)k a)ntimarturei=tai toi=s <!-- ref: 88,2 --><lb/>
par' h(mi=n ginome/nois pleonaxw=s suntelei=sqai. <!-- ref: 88,3 --><lb/>
</s></p><p><s>*ko/smos e)sti\ perioxh\ tis ou)ranou=, a)/stra te kai\ gh=n kai\  <!-- ref: 88,4 --><lb/>
pa/nta ta\ faino/mena perie/xousa, a)potomh\n e)/xousa a)po\ tou= <!-- ref: 88,5 --><lb/>
a)pei/rou, kai\ katalh/gousa e)n pe/rati h)\ a)raiw=| h)\ puknw=|_kai\ <!-- ref: 88,6 --><lb/>
ou(= luome/nou pa/nta ta\ e)n au)tw=| su/gxusin lh/yetai_[kai\ lh/&shy;<!-- ref: 88,7 --><lb/>
gousan] h)\ [e)n] periagome/nw| h)\ [e)n] sta/sin e)/xonti, kai\ strog&shy;<!-- ref: 88,8 --><lb/>
gu/lhn h)\ tri/gwnon h)\ oi(/an dh/pote perigrafh/n: pantaxw=s ga\r <!-- ref: 88,9 --><lb/>
e)nde/xetai: tw=n ga\r fainome/nwn ou)de\n a)ntimarturei= tw=|de tw=| <!-- ref: 88,10 --><lb/>
ko/smw| e)n w(=| lh=gon ou)k e)/sti katalabei=n. </s><s><!-- ref: 88,11 --><lb/>
*(/oti de\ kai\ toiou=toi <!-- ref: 89,1 --><lb/>
ko/smoi ei)si\n a)/peiroi to\ plh=qos e)/sti katalabei=n, kai\ o(/ti kai\ <!-- ref: 89,2 --><lb/>
o( toiou=tos du/natai ko/smos gi/nesqai kai\ e)n ko/smw| kai\ meta&shy;<!-- ref: 89,3 --><lb/>
kosmi/w|, o(\ le/gomen metacu\ ko/smwn <pb pagenum="260"/>dia/sthma, e)n poluke/nw| <!-- ref: 89,4 --><lb/>
to/pw| kai\ ou)k e)n mega/lw| ei)likrinei= kai\ kenw=|, kaqa/per tine/s <!-- ref: 89,5 --><lb/>
fasin, e)pithdei/wn tinw=n sperma/twn r(ue/ntwn a)f' e(no\s ko/smou <!-- ref: 89,6 --><lb/>
h)\ metakosmi/ou h)\ a)po\ pleio/nwn kata\ mikro\n prosqe/seis te kai\ <!-- ref: 89,7 --><lb/>
diarqrw/seis kai\ metasta/seis poiou/ntwn e)p' a)/llon to/pon, e)a\n <!-- ref: 89,8 --><lb/>
ou(/tw tu/xh|, kai\ e)pardeu/seis e)k tw=n e)xo/ntwn e)pithdei/ws e(/ws <!-- ref: 89,9 --><lb/>
teleiw/sews kai\ diamonh=s e)f' o(/son ta\ u(poblhqe/nta qeme/lia th\n <!-- ref: 89,10 --><lb/>
prosdoxh\n du/natai poiei=sqai: <!-- ref: 89,11 --><lb/>
ou) ga\r a)qroismo\n dei= mo/non ge&shy;<!-- ref: 90,1 --><lb/>
ne/sqai ou)de\ di=non e)n w(=| e)nde/xetai ko/smon gi/nesqai kenw=| kata\ <!-- ref: 90,2 --><lb/>
to\ docazo/menon e)c a)na/gkhs, au)/cesqai/ te e(/ws a)\n e(te/rw| pros&shy;<!-- ref: 90,3 --><lb/>
krou/sh|, kaqa/per tw=n fusikw=n kaloume/nwn fhsi/ tis. </s><s>tou=to ga\r <!-- ref: 90,4 --><lb/>
maxo/meno/n e)sti toi=s fainome/nois. <!-- ref: 90,5 --><lb/>
</s></p><p><s>*(/hlio/s te kai\ selh/nh kai\ ta\ loipa\ a)/stra &lt;ou)&gt; kaq' e(auta\ <!-- ref: 90,6 --><lb/>
geno/mena u(/steron e)mperielamba/neto u(po\ tou= ko/smou kai\ o(/sa <!-- ref: 90,7 --><lb/>
ge dh\ sw/|zei, a)ll' eu)qu\s diepla/tteto kai\ au)/chsin e)la/mbanen, <!-- ref: 90,8 --><lb/>
o(moi/ws de\ kai\ gh= kai\ qa/latta, kata\ proskri/seis kai\ dinh/seis <!-- ref: 90,9 --><lb/>
leptomerw=n tinwn fu/sewn, h)/toi pneumatikw=n h)\ puroeidw=n h)\ to\ <!-- ref: 90,10 --><lb/>
sunamfo/teron: kai\ ga\r tau=ta ou(/tws h( ai)/sqhsis u(poba/llei.  <!-- ref: 91,1 --><lb/>
</s></p><p><s>*to\ de\ me/geqos h(li/ou te kai\ tw=n loipw=n a)/strwn kata\ me\n to\ <!-- ref: 91,2 --><lb/>
pro\s h(ma=s thlikou=to/n e)stin h(li/kon fai/netai, &lpar;tou=to kai\ <!-- ref: 91,3 --><lb/>
e)n th=| &lt;i&gt; </s><s>&lt;a&gt; </s><s>*peri\ fu/sews: ei) ga\r, fhsi/, to\ me/geqos dia\ to\ <!-- ref: 91,4 --><lb/>
dia/sthma a)pobeblh/kei, pollw=| ma=llon a)\n th\n xro/an: a)/llo ga\r <!-- ref: 91,5 --><lb/>
tou/tw| summetro/teron dia/sthma ou)qe/n e)sti.&rpar; kata\ de\ to\ kaq' <!-- ref: 91,6 --><lb/>
au(to\ h)/toi mei=zon tou= o(rw&shy;<pb pagenum="261"/>me/nou h)\ mikrw=| e)/latton h)\ thlikou=ton <!-- ref: 91,7 --><lb/>
[ou)x a(/ma]. </s><s>ou(/tw ga\r kai\ ta\ par' h(mi=n pura\ e)c a)posth/matos <!-- ref: 91,8 --><lb/>
qewrou/mena kata\ th\n ai)/sqhsin qewrei=tai. </s><s>kai\ pa=n de\ to\ ei)s <!-- ref: 91,9 --><lb/>
tou=to to\ me/ros e)/nsthma r(a|di/ws dialuqh/setai e)a/n tis toi=s e)nar&shy;<!-- ref: 91,10 --><lb/>
gh/masi prose/xh|, o(/per e)n toi=s peri\ fu/sews bibli/ois dei/knumen. </s><s><!-- ref: 91,11 --><lb/>
*)anatola\s kai\ du/seis h(li/ou kai\ selh/nhs kai\ tw=n loipw=n a)/strwn <!-- ref: 92,1 --><lb/>
kai\ kata\ a)/nayin gi/nesqai du/nasqai kai\ kata\ sbe/sin, toiau/ths <!-- ref: 92,2 --><lb/>
ou)/shs perista/sews kai\ kaq' e(kate/rous tou\s to/pous, w(/ste ta\ <!-- ref: 92,3 --><lb/>
proeirhme/na a)potelei=sqai: ou)de\n ga\r tw=n fainome/nwn a)ntimar&shy;<!-- ref: 92,4 --><lb/>
turei=: &lt;kai\&gt; kat' e)kfa/neia/n te u(pe\r gh=s kai\ pa/lin e)piprosqe/&shy;<!-- ref: 92,5 --><lb/>
thsin to\ proeirhme/non du/nait' a)\n suntelei=sqai: ou)de\ ga/r ti <!-- ref: 92,6 --><lb/>
tw=n fainome/nwn a)ntimarturei=. </s><s>*ta/s te kinh/seis au)tw=n ou)k a)du/&shy;<!-- ref: 92,7 --><lb/>
naton me\n gi/nesqai kata\ th\n tou= o(/lou ou)ranou= di/nhn, h)\ tou/tou <!-- ref: 92,8 --><lb/>
me\n sta/sin, au)tw=n de\ di/nhn kata\ th\n e)c a)rxh=s e)n th=| gene/sei <!-- ref: 92,9 --><lb/>
tou= ko/smou a)na/gkhn a)pogennhqei=san e)p' a)natolh=|, <!-- ref: 92,10 --><lb/>
ei)=ta th=| <!-- ref: 93,1 --><lb/>
qermasi/a|, kata/ tina e)pine/mhsin tou= puro\s a)ei\ e)pi\ tou\s e(ch=s <!-- ref: 93,2 --><lb/>
to/pous i)o/ntos. </s><s>*tropa\s h(li/ou kai\ selh/nhs e)nde/xetai me\n gi/&shy;<!-- ref: 93,3 --><lb/>
nesqai kata\ lo/cwsin ou)ranou= ou(/tw toi=s xro/nois kathnagka&shy;<!-- ref: 93,4 --><lb/>
sme/nou: o(moi/ws de\ kai\ kata\ a)e/ros a)nte/cwsin h)\ kai\ u(/lhs a)ei\  <!-- ref: 93,5 --><lb/>
e)pithdei/as e)xome/nois e)mpiprame/nhs th=s de\ katalipou/shs, h)\| <!-- ref: 93,6 --><lb/>
kai\ e)c a)rxh=s toiau/thn di/nhn kateilhqh=nai toi=s a)/strois tou/&shy;<!-- ref: 93,7 --><lb/>
tois, w(/sq' oi(=o/n tin' e(/lika kinei=sqai: pa/nta ga\r ta\ toiau=ta kai\ <!-- ref: 93,8 --><lb/>
ta\ tou/tois suggenh= ou)qeni\ tw=n e)narghma/twn diafwnei=, e)a/n tis <!-- ref: 93,9 --><lb/>
a)ei\ e)pi\ tw=n toiou/twn merw=n e)xo/menos tou= dunatou= ei)s to\ su/m&shy;<!-- ref: 93,10 --><lb/>
fwnon toi=s <pb pagenum="262"/>fainome/nois e(/kaston tou/twn du/nhtai e)pa/gein, mh\ <!-- ref: 93,11 --><lb/>
fobou/menos ta\s a)ndrapodw/deis a)strolo/gwn texnitei/as. <!-- ref: 93,12 --><lb/>
</s></p><p><s>*kenw/seis te selh/nhs kai\ pa/lin plhrw/seis kai\ kata\ strofh\n <!-- ref: 94,1 --><lb/>
tou= sw/matos tou/tou du/naint' a)\n gi/nesqai, kai\ kata\ sxhmati&shy;<!-- ref: 94,2 --><lb/>
smou\s a)e/ros o(moi/ws, e)/ti te kai\ kata\ prosqeth/seis kai\ kata\ <!-- ref: 94,3 --><lb/>
pa/ntas tro/pous kaq' ou(\s kai\ ta\ par' h(mi=n faino/mena e)kka&shy;<!-- ref: 94,4 --><lb/>
lei=tai ei)s ta\s tou/tou tou= ei)/dous a)podo/seis, e)a\n mh/ tis to\n <!-- ref: 94,5 --><lb/>
monaxh=| tro/pon kathgaphkw\s tou\s a)/llous kenw=s a)podokima/zh|, <!-- ref: 94,6 --><lb/>
ou) teqewrhkw\s ti/ dunato\n a)nqrw/pw| qewrh=sai kai\ ti/ a)du/naton, <!-- ref: 94,7 --><lb/>
kai\ dia\ tou=to a)du/nata qewrei=n e)piqumw=n. </s><s>*)/eti te e)nde/xetai <!-- ref: 94,8 --><lb/>
&lt;me\n&gt; th\n selh/nhn e)c e(auth=s e)/xein to\ fw=s, e)nde/xetai de\ a)po\ <!-- ref: 94,9 --><lb/>
tou= h(li/ou. </s><s><!-- ref: 94,10 --><lb/>
kai\ ga\r par' h(mi=n qewrei=tai polla\ me\n e)c e(autw=n <!-- ref: 95,1 --><lb/>
e)/xonta, polla\ de\ a)f' e(te/rwn: kai\ ou)qe\n e)mpodostatei= tw=n e)n <!-- ref: 95,2 --><lb/>
toi=s metew/rois fainome/nwn, e)a/n tis tou= pleonaxou= tro/pou a)ei\ <!-- ref: 95,3 --><lb/>
mnh/mhn e)/xh| kai\ ta\s a)kolou/qous au)toi=s u(poqe/seis a(/ma kai\ ai)&shy;<!-- ref: 95,4 --><lb/>
ti/as sunqewrh=| kai\ mh\ a)nable/pwn ei)s ta\ a)nako/louqa tau=t' <!-- ref: 95,5 --><lb/>
o)gkoi= matai/ws kai\ katarre/ph| a)/llote a)/llws e)pi\ to\n monaxo\n <!-- ref: 95,6 --><lb/>
tro/pon. </s><s>*(h de\ e)/mfasis tou= prosw/pou e)n au)th=| du/natai me\n gi/&shy;<!-- ref: 95,7 --><lb/>
nesqai kai\ kata\ parallagh\n merw=n kai\ kat' e)piprosqe/thsin,  <!-- ref: 95,8 --><lb/>
kai\ o(/soi pot' a)\n tro/poi qewroi=nto to\ su/mfwnon toi=s fainome/&shy;<!-- ref: 95,9 --><lb/>
nois kekthme/noi: <!-- ref: 95,10 --><lb/>
e)pi\ pa/ntwn ga\r tw=n metew/rwn th\n toiau/thn <!-- ref: 96,1 --><lb/>
i)/xneusin ou) proete/on. </s><s>h)\n ga/r tis h)=| maxo/menos toi=s e)nargh/masin, <!-- ref: 96,2 --><lb/>
ou)de/pote mh\ dunh/setai a)taraci/as gnh&shy;<pb pagenum="263"/>si/ou metalabei=n. <!-- ref: 96,3 --><lb/>
</s></p><p><s>*)/ekleiyis h(li/ou kai\ selh/nhs du/natai me\n gi/nesqai kai\ kata\ <!-- ref: 96,4 --><lb/>
sbe/sin, kaqa/per kai\ para\ h(mi=n tou=to qewrei=tai gino/menon: kai\ <!-- ref: 96,5 --><lb/>
h)/dh kat' e)piprosqe/thsin a)/llwn tinw=n, h)\ gh=s h)\ ou)ranou= [h)/] <!-- ref: 96,6 --><lb/>
tinos e(te/rou toiou/tou. </s><s>kai\ w(=de tou\s oi)kei/ous a)llh/lois tro/&shy;<!-- ref: 96,7 --><lb/>
pous sunqewrhte/on, kai\ ta\s a(/ma sugkurh/seis tinw=n o(/ti ou)k a)du/&shy;<!-- ref: 96,8 --><lb/>
naton gi/nesqai. </s><s>&lpar;e)n de\ th=| &lt;i&gt; </s><s>&lt;b&gt; </s><s>*peri\ fu/sews tau)ta\ le/&shy;<!-- ref: 96,9 --><lb/>
gei kai\ pro/s, h(/lion e)klei/pein selh/nhs e)piskotou/shs, selh/nhn de\ <!-- ref: 96,10 --><lb/>
tou= th=s gh=s skia/smatos, a)lla\ kai\ kat' a)naxw/rhsin: <!-- ref: 96,11 --><lb/>
tou=to de\ <!-- ref: 97,1 --><lb/>
kai\ *dioge/nhs o( *)epikou/reios e)n th=| &lt;a&gt; </s><s>tw=n *)epile/ktwn.&rpar; *)/eti te <!-- ref: 97,2 --><lb/>
ta/cis perio/dou, kaqa/per e)/nia kai\ par' h(mi=n tw=n tuxo/ntwn gi/&shy;<!-- ref: 97,3 --><lb/>
netai, lambane/sqw: kai\ h( qei/a fu/sis pro\s tau=ta mhdamh=| pro&shy;<!-- ref: 97,4 --><lb/>
sage/sqw, a)ll' a)leitou/rghtos diathrei/sqw kai\ e)n th=| pa/sh| ma&shy;<!-- ref: 97,5 --><lb/>
kario/thti. </s><s>w(s ei) tou=to mh\ praxqh/setai a(/pasa h( tw=n metew/rwn <!-- ref: 97,6 --><lb/>
ai)tiologi/a matai/a e)/stai, kaqa/per tisi\n h)/dh e)ge/neto ou) dunatou= <!-- ref: 97,7 --><lb/>
tro/pou e)fayame/nois, ei)s de\ to\ ma/taion e)kpesou=si tw=| kaq' e(/na <!-- ref: 97,8 --><lb/>
tro/pon mo/non oi)/esqai gi/nesqai, tou\s d' a)/llous pa/ntas tou\s kata\ <!-- ref: 97,9 --><lb/>
to\ e)ndexo/menon e)kba/llein, ei)/s te to\ a)diano/hton ferome/nous kai\ <!-- ref: 97,10 --><lb/>
ta\ faino/mena a(\ dei= shmei=a a)pode/xesqai mh\ duname/nous sun&shy;<!-- ref: 97,11 --><lb/>
qewrei=n.  <!-- ref: 97,12 --><lb/>
</s></p><p><s>*mh/kh nuktw=n kai\ h(merw=n paralla/ttonta kai\ para\ to\ ta&shy;<!-- ref: 98,1 --><lb/>
xei/as h(li/ou kinh/seis gi/nesqai kai\ pa/lin bradei/as u(pe\r gh=s <!-- ref: 98,2 --><lb/>
&lt;h)\ kai\&gt; para\ to\ mh/kh to/pwn paralla/ttonta kai\ to/pous tina\s <!-- ref: 98,3 --><lb/>
peraiou=n ta/xion h)\ kai\ bradu/teron, w(s kai\ para\ h(mi=n <pb pagenum="264"/>tina qew&shy;<!-- ref: 98,4 --><lb/>
rei=tai, oi(=s sumfw/nws dei= le/gein e)pi\ tw=n metew/rwn. </s><s>oi( de\ to\ <!-- ref: 98,5 --><lb/>
e(\n lamba/nontes toi=s te fainome/nois ma/xontai kai\ to\ h(=| dunato\n <!-- ref: 98,6 --><lb/>
a)nqrw/pw| qewrh=sai diapeptw/kasin. <!-- ref: 98,7 --><lb/>
</s></p><p><s>*)epishmasi/ai du/nantai gi/nesqai kai\ kata\ sugkurh/seis kai&shy;<!-- ref: 98,8 --><lb/>
rw=n, kaqa/per e)n toi=s e)mfane/si par' h(mi=n zw=|ois, kai\ par' e(te&shy;<!-- ref: 98,9 --><lb/>
roiw/seis a)e/ros kai\ metabola/s: a)mfo/tera ga\r tau=ta ou) ma/xetai <!-- ref: 98,10 --><lb/>
toi=s fainome/nois: <!-- ref: 98,11 --><lb/>
e)pi\ de\ poi/ois para\ tou=to h)\ tou=to to\ ai)/tion <!-- ref: 99,1 --><lb/>
gi/netai ou)k e)/sti sunidei=n. <!-- ref: 99,2 --><lb/>
</s></p><p><s>*ne/fh du/natai gi/nesqai kai\ suni/stasqai kai\ para\ pilh/seis <!-- ref: 99,3 --><lb/>
a)e/ros pneuma/twn sunw/sei kai\ para\ periploka\s a)llhlou/xwn <!-- ref: 99,4 --><lb/>
a)to/mwn kai\ e)pithdei/wn ei)s to\ tou=to tele/sai, kai\ kata\ r(euma/&shy;<!-- ref: 99,5 --><lb/>
twn sullogh\n a)po/ te gh=s kai\ u(da/twn: kai\ kat' a)/llous de\ tro/&shy;<!-- ref: 99,6 --><lb/>
pous plei/ous ai( tw=n toiou/twn susta/seis ou)k a)dunatou=si sun&shy;<!-- ref: 99,7 --><lb/>
telei=sqai. </s><s>*)/hdh d' a)p' au)tw=n h(=| me\n qlibome/nwn h(=| de\ metabal&shy;<!-- ref: 99,8 --><lb/>
lo/ntwn u(/data du/natai suntelei=sqai: <!-- ref: 99,9 --><lb/>
e)/ti te pneu/mata kata\ <!-- ref: 100,1 --><lb/>
a)pofora\n a)po\ e)pithdei/wn to/pwn, kai\ di' a)e/ros kinoume/nou, <!-- ref: 100,2 --><lb/>
biaiote/ras e)pardeu/sews ginome/nhs a)po/ tinwn a)qroisma/twn e)pi&shy;<!-- ref: 100,3 --><lb/>
thdei/wn ei)s ta\s toiau/tas e)pipe/myeis. <!-- ref: 100,4 --><lb/>
</s></p><p><s>*bronta\s e)nde/xetai gi/nesqai kai\ kata\ pneu/matos e)n toi=s <!-- ref: 100,5 --><lb/>
koilw/masi tw=n nefw=n a)nei/lhsin, kaqa/per e)n toi=s h(mete/rois a)g&shy;<!-- ref: 100,6 --><lb/>
gei/ois kai\ para\ puro\s pepneumatwme/nou bo/mbon e)n au)toi=s, kai\  <!-- ref: 100,7 --><lb/>
kata\ r(h/ceis de\ nefw=n kai\ diasta/seis, kai\ kata\ paratri/yeis <!-- ref: 100,8 --><lb/>
nefw=n kai\ kata/ceis ph=cin ei)lhfo/twn krustalloeidh=: kai\ to\ <!-- ref: 100,9 --><lb/><pb pagenum="265"/>
o(/lon kai\ tou=to to\ me/ros pleonaxw=s gi/nesqai le/gein e)kkalei=tai <!-- ref: 100,10 --><lb/>
ta\ faino/mena. </s><s><!-- ref: 100,11 --><lb/>
*kai\ a)strapai\ d' w(sau/tws gi/nontai kata\ plei/ous <!-- ref: 101,1 --><lb/>
tro/pous: kai\ ga\r kata\ para/triyin kai\ su/gkrousin nefw=n o( <!-- ref: 101,2 --><lb/>
puro\s a)potelestiko\s sxhmatismo\s e)colisqai/nwn a)straph\n gen&shy;<!-- ref: 101,3 --><lb/>
na=|. </s><s>kai\ kat' e)kripismo\n e)k tw=n nefw=n u(po\ pneuma/twn tw=n toiou/&shy;<!-- ref: 101,4 --><lb/>
twn swma/twn a(\ th\n lamphdo/na tau/thn paraskeua/zei: kai\ kat' <!-- ref: 101,5 --><lb/>
e)kpiasmo/n, qli/yews tw=n nefw=n ginome/nhs ei)/q' u(p' a)llh/lwn ei)/q' <!-- ref: 101,6 --><lb/>
u(po\ pneuma/twn: kai\ kat' e)mperi/lhyin de\ tou= a)po\ tw=n a)/strwn <!-- ref: 101,7 --><lb/>
katesparme/nou fwto/s, ei)=ta sunelaunome/nou u(po\ th=s kinh/sews <!-- ref: 101,8 --><lb/>
nefw=n te kai\ pneuma/twn kai\ diekpi/ptontos dia\ tw=n nefw=n, h)\ <!-- ref: 101,9 --><lb/>
kata\ dih/qhsin &lt;dia\&gt; tw=n nefw=n tou= leptomeresta/tou fwto/s: h)\ <!-- ref: 101,10 --><lb/>
a)po\ tou= puro\s ne/fh suneile/xqai kai\ ta\s bronta\s a)potelei=sqai <!-- ref: 101,11 --><lb/>
[kai\] kata\ th\n tou/tou ki/nhsin. </s><s>kai\ kata\ th\n tou= pneu/matos <!-- ref: 101,12 --><lb/>
e)kpu/rwsin th\n ginome/nhn dia/ te suntoni/an fora=s kai\ dia\ sfodra\n <!-- ref: 101,13 --><lb/>
katei/lhsin: <!-- ref: 101,14 --><lb/>
kai\ kata\ r(h/ceis de\ nefw=n u(po\ pneuma/twn e)/kptw&shy;<!-- ref: 102,1 --><lb/>
si/n te puro\s a)potelestikw=n a)to/mwn kai\ to\ th=s a)straph=s fa/n&shy;<!-- ref: 102,2 --><lb/>
tasma a)potelousw=n: kai\ kat' a)/llous de\ plei/ous tro/pous r(a|di/ws <!-- ref: 102,3 --><lb/>
e)/stai kaqora=n e)xo/menon a)ei\ tw=n fainome/nwn kai\ to\ tou/tois <!-- ref: 102,4 --><lb/>
o(/moion duna/menon sunqewrei=n. </s><s>*proterei= de\ a)straph\ bronth=s e)n <!-- ref: 102,5 --><lb/>
toia=|de/ tini perista/sei nefw=n kai\ dia\ to\ a(/ma tw=| to\ pneu=ma <!-- ref: 102,6 --><lb/>
e)mpi/ptein e)cwqei=sqai to\n a)straph=s a)potelestiko\n sxhmati&shy;<!-- ref: 102,7 --><lb/>
smo/n, u(/steron de\ to\ pneu=ma a)neilou/menon to\n bo/mbon a)potelei=n <!-- ref: 102,8 --><lb/>
tou=ton: kai\ kat' e)/mptwsin de\ a)mfote/rwn <pb pagenum="266"/>a(/ma tw=| ta/xei sunto- <!-- ref: 102,9 --><lb/>
nwte/rw| kexrh=sqai pro\s h(ma=s th\n a)straph/n, <!-- ref: 102,10 --><lb/>
u(sterei=n de\ th\n <!-- ref: 103,1 --><lb/>
bronth/n, kaqa/per e)p' e)ni/wn e)c a)posth/matos qewroume/nwn kai\ <!-- ref: 103,2 --><lb/>
plhga/s tinas poioume/nwn. <!-- ref: 103,3 --><lb/>
</s></p><p><s>*kerauno\s e)nde/xetai gi/nesqai kai\ kata\ plei/onas pneuma/twn <!-- ref: 103,4 --><lb/>
sulloga\s kai\ katei/lhsin i)sxura/n te e)kpu/rwsin kai\ kata/rrhcin <!-- ref: 103,5 --><lb/>
me/rous kai\ e)/kptwsin i)sxurote/ran au)tou= e)pi\ tou\s ka/tw to/pous, <!-- ref: 103,6 --><lb/>
th=s r(h/cews ginome/nhs dia\ to\ tou\s e(ch=s to/pous puknote/rous <!-- ref: 103,7 --><lb/>
ei)=nai dia\ pi/lhsin nefw=n: kai\ kat' au)th\n de\ th\n tou= puro\s e)/k&shy;<!-- ref: 103,8 --><lb/>
ptwsin a)neiloume/nou, kaqa\ kai\ bronth\n e)nde/xetai gi/nesqai, <!-- ref: 103,9 --><lb/>
plei/onos genome/nou kai\ pneumatwqe/ntos i)sxuro/teron kai\ r(h/&shy;<!-- ref: 103,10 --><lb/>
cantos to\ ne/fos dia\ to\ mh\ du/nasqai u(poxwrei=n ei)s ta\ e(ch=s, <!-- ref: 103,11 --><lb/>
tw=| pi/lhsin gi/nesqai, to\ me\n polu\ pro\s o(/ros ti u(yhlo/n, e)n w(=| <!-- ref: 103,12 --><lb/>
ma/lista keraunoi\ pi/ptousin, a)ei\ &lt;de\&gt; pro\s a)/llhla. </s><s><!-- ref: 103,13 --><lb/>
kai\ kat' <!-- ref: 104,1 --><lb/>
a)/llous de\ tro/pous plei/onas e)nde/xetai kerauno\s a)potelei=sqai: <!-- ref: 104,2 --><lb/>
mo/non o( mu=qos a)pe/stw: a)pe/stai de/, e)a/n tis kalw=s toi=s faino&shy;<!-- ref: 104,3 --><lb/>
me/nois a)kolouqw=n peri\ tw=n a)fanw=n shmeiw=tai. <!-- ref: 104,4 --><lb/>
</s></p><p><s>*prhsth=ras e)nde/xetai ginesqai kai\ kata\ ka/qesin ne/fous ei)s <!-- ref: 104,5 --><lb/>
tou\s ka/tw to/pous stuloeidw=s u(po\ pneu/matos a)qro/ou w)sqe/ntos, <!-- ref: 104,6 --><lb/>
kai\ dia\ tou= pneu/matos pollou= ferome/nou, a(/ma kai\ to\ ne/fos <!-- ref: 104,7 --><lb/>
ei)s to\ pla/gion w)qou=ntos tou= e)kto\s pneu/matos: kai\ kata\ peri/&shy;<!-- ref: 104,8 --><lb/>
stasin de\ pneu/matos ei)s ku/klon, a)e/ros tino\s e)pisunwqoume/nou <!-- ref: 104,9 --><lb/>
a)/nwqen kai\ r(u/sews pollh=s pneuma/twn ginome/nhs kai\ ou) du&shy;<!-- ref: 104,10 --><lb/>
name/nhs ei)s ta\ pla/gia diarruh=nai dia\ th\n pe/&shy;<pb pagenum="266"/>ric tou= a)e/ros <!-- ref: 104,11 --><lb/>
pi/lhsin. </s><s><!-- ref: 104,12 --><lb/>
kai\ e(/ws me\n gh=s tou= prhsth=ros kaqieme/nou stro/&shy;<!-- ref: 105,1 --><lb/>
biloi gi/nontai, w(s a)\n kai\ h( a)poge/nnhsis kata\ th\n ki/nhsin tou= <!-- ref: 105,2 --><lb/>
pneu/matos gi/nhtai, e(/ws de\ qala/tths di=noi a)potelou=ntai. <!-- ref: 105,3 --><lb/>
</s></p><p><s>*seismou\s e)nde/xetai gi/nesqai kai\ kata\ pneu/matos e)n th=| gh=|  <!-- ref: 105,4 --><lb/>
a)po/lhyin kai\ para\ mikrou\s o)/gkous au)th=s para/qesin kai\ su&shy;<!-- ref: 105,5 --><lb/>
nexh= ki/nhsin, o(\ th\n kra/dansin th=| gh=| paraskeua/zei. </s><s>kai\ to\ pneu=&shy;<!-- ref: 105,6 --><lb/>
ma tou=to h)\ e)/cwqen e)mperilamba/nei &lt;h)\&gt; e)k tou= pi/ptein [ei)s] <!-- ref: 105,7 --><lb/>
e)da/fh ei)s a)ntroeidei=s to/pous th=s gh=s e)kpneumatou=nta to\n pe&shy;<!-- ref: 105,8 --><lb/>
pilhme/non a)e/ra: &lt;kai\&gt; kat' au)th\n de\ th\n dia/dosin th=s kinh/sews <!-- ref: 105,9 --><lb/>
e)k tw=n ptw/sewn e)dafw=n pollw=n kai\ pa/lin a)ntapo/dosin, o(/tan <!-- ref: 105,10 --><lb/>
puknw/masi sfodrote/rois th=s gh=s a)panth/sh|, e)nde/xetai seismou\s <!-- ref: 105,11 --><lb/>
a)potelei=sqai. </s><s><!-- ref: 105,12 --><lb/>
kai\ kat' a)/llous de\ plei/ous tro/pous ta\s kinh/seis <!-- ref: 106,1 --><lb/>
tau/tas th=s gh=s gi/nesqai. <!-- ref: 106,2 --><lb/>
</s></p><p><s>*ta\ de\ pneu/mata sumbai/nei gi/nesqai kata\ xro/non a)llofu&shy;<!-- ref: 106,3 --><lb/>
li/as tino\s a)ei\ kai\ kata\ mikro\n pareisduome/nhs, kai\ kaq' u(/datos <!-- ref: 106,4 --><lb/>
a)fqo/nou sullogh/n. </s><s>to\ de\ loipo\n pneu/mata gi/netai kai\ o)li/gwn <!-- ref: 106,5 --><lb/>
peso/ntwn ei)s ta\ polla\ koilw/mata, diado/sews tou/twn ginome/nhs. <!-- ref: 106,6 --><lb/>
</s></p><p><s>*xa/laza suntelei=tai kai\ kata\ ph=cin i)sxurote/ran, pa/ntoqen <!-- ref: 106,7 --><lb/>
de\ pneumatwdw=n peri/stasi/n tinwn, kai\ katame/risin: kai\ th=cin <!-- ref: 106,8 --><lb/>
metriwte/ran u(datoeidw=n tinwn, o(mou= r(h=cin a(/ma th/n te su/nwsin <!-- ref: 106,9 --><lb/>
au)tw=n poioume/nhn kai\ th\n dia/rrhcin pro\s to\ kata\ me/rh sun&shy;<!-- ref: 106,10 --><lb/>
i/stasqai phgnu/mena kai\ kata\ a)qro/thta: <!-- ref: 106,11 --><lb/>
h( de\ perife/reia ou)k <!-- ref: 107,1 --><lb/>
a)duna/tws me\n e)/xei gi/nesqai pa/ntoqen tw=n a)/krwn a)pothkome/nwn <!-- ref: 107,2 --><lb/>
kai\ e)n th=| susta/sei pa/ntoqen, w(s le/getai,<pb pagenum="267"/> kata\ me/rh o(malw=s <!-- ref: 107,3 --><lb/>
periistame/nwn ei)/te u(datoeidw=n tinwn, ei)/te pneumatodw=n. <!-- ref: 107,4 --><lb/>
</s></p><p><s>*xio/na de\ e)nde/xetai suntelei=sqai kai\ u(/datos leptou= e)kxeo&shy;<!-- ref: 107,5 --><lb/>
me/nou e)k tw=n nefw=n, dia\ po/rwn summetri/as kai\ qli/yews e)pith&shy;<!-- ref: 107,6 --><lb/>
dei/wn nefw=n a)ei\ u(po\ pneu/matos sfodra=s, ei)=ta tou/tou ph=cin  <!-- ref: 107,7 --><lb/>
e)n th=| fora=| lamba/nontos dia/ tina i)sxura\n e)n toi=s katw/teron <!-- ref: 107,8 --><lb/>
to/pois tw=n nefw=n yuxrasi/as peri/stasin: kai\ kata\ ph=cin d' e)n <!-- ref: 107,9 --><lb/>
toi=s ne/fesin o(malh= a)raio/thta e)/xousan toiau/th pro/esis e)k tw=n <!-- ref: 107,10 --><lb/>
nefw=n gi/noito a)/n, pro\s a)/llhla qlibome/nwn u(datoeidw=n tinwn <!-- ref: 107,11 --><lb/>
sumparakeime/nwn, a(\ oi(onei\ su/nwsin poiou/mena xa/lazan a)po&shy;<!-- ref: 107,12 --><lb/>
telei=, o(\ ma/lista gi/netai e)n tw=| e)/ari: <!-- ref: 107,13 --><lb/>
kai\ kata\ tri=yin de\ nefw=n <!-- ref: 108,1 --><lb/>
ph=cin ei)lhfo/twn a)po/palsin a)\n lamba/noi to\ th=s xio/nos tou=to <!-- ref: 108,2 --><lb/>
a)/qroisma. </s><s>kai\ kat' a)/llous de\ tro/pous e)nde/xetai xio/na sun&shy;<!-- ref: 108,3 --><lb/>
telei=sqai. <!-- ref: 108,4 --><lb/>
</s></p><p><s>*dro/sos suntelei=tai kai\ kata\ su/nodon pro\s a)/llhla e)k tou= <!-- ref: 108,5 --><lb/>
a)e/ros tw=n toiou/twn, a(\ th=s toiau/ths u(grasi/as a)potelestika\ gi/&shy;<!-- ref: 108,6 --><lb/>
netai: kai\ kata\ fora\n de\ h)\ a)po\ noterw=n to/pwn h)\ u(/data kekth&shy;<!-- ref: 108,7 --><lb/>
me/nwn, e)n oi(=s to/pois ma/lista dro/sos suntelei=tai, ei)=ta su/nodon <!-- ref: 108,8 --><lb/>
tou/twn ei)s to\ au)to\ labo/ntwn kai\ a)pote/lesin u(grasi/as kai\ pa/&shy;<!-- ref: 108,9 --><lb/>
lin fora\n e)pi\ tou\s ka/tw to/pous, kaqa/per o(moi/ws kai\ par' <!-- ref: 108,10 --><lb/>
h(mi=n e)pi\ pleio/nwn toiau=ta/ tina suntelei=tai. </s><s><!-- ref: 108,11 --><lb/>
&lt;*pa/xnh de\ sun&shy;<!-- ref: 109,1 --><lb/>
telei=tai&gt; tw=n dro/swn tou/twn ph=ci/n tina poia\n labo/ntwn dia\ <!-- ref: 109,2 --><lb/>
peri/stasi/n tina a)e/ros yuxrou=. <!-- ref: 109,3 --><lb/>
</s></p><p><s>*kru/stallos suntelei=tai kai\ kat' e)/kqliyin me\n tou= peri&shy;<!-- ref: 109,4 --><lb/>
ferou=s sxhmatismou= e)k tou= u(/datos, su/nwsin de\ tw=n <pb pagenum="268"/>skalhnw=n <!-- ref: 109,5 --><lb/>
kai\ o)cugwni/wn tw=n e)n th=| u(/dati u(parxo/ntwn, kai\ kata\ e)/cwqen <!-- ref: 109,6 --><lb/>
de\ tw=n toiou/twn pro/skrisin, a(\ sunelasqe/nta ph=cin tw=| u(/dati <!-- ref: 109,7 --><lb/>
pareskeu/ase, posa\ tw=n periferw=n e)kqli/yanta. <!-- ref: 109,8 --><lb/>
</s></p><p><s>*)=iris gi/netai kata\ pro/slamyin [u(po\] tou= h(li/ou pro\s a)e/ra <!-- ref: 109,9 --><lb/>
u(datoeidh=, h)\ kata\ pro/sfusin i)di/an tou= te fwto\s kai\ tou= a)e/ros, <!-- ref: 109,10 --><lb/>
h(\ ta\ tw=n xrwma/twn tou/twn i)diw/mata poih/sei ei)/te pa/nta ei)/te <!-- ref: 109,11 --><lb/>
monoeidw=s, a)f' ou(= pa/lin a)pola/mpontos ta\ o(morou=nta tou= a)e/ros  <!-- ref: 109,12 --><lb/>
xrw=sin tau/thn lh/yetai, oi(/an qewrou=men, kata\ pro/slamyin pro\s <!-- ref: 109,13 --><lb/>
ta\ me/rh. </s><s><!-- ref: 109,14 --><lb/>
*to\ de\ th=s periferei/as tou=tou fa/ntasma gi/netai dia\ <!-- ref: 110,1 --><lb/>
to\ to\ dia/sthma pa/ntoqen i)/son u(po\ th=s o)/yews qewrei=sqai, h)\ <!-- ref: 110,2 --><lb/>
su/nwsin toiau/thn lambanousw=n tw=n e)n tw=| a)e/ri &lt;a)&gt;to/mwn h)\ e)n <!-- ref: 110,3 --><lb/>
toi=s ne/fesin a)po\ tou= au)tou= a)e/ros [prosferome/nou pro\s th\n <!-- ref: 110,4 --><lb/>
selh/nhn]: a)poferome/nwn a)to/mwn perife/reia/n tina kaqi/esqai <!-- ref: 110,5 --><lb/>
th\n su/gkrisin tau/thn. <!-- ref: 110,6 --><lb/>
</s></p><p><s>*)/alws peri\ th\n selh/nhn gi/netai [kai\ kata\] pa/ntoqen a)e/ros <!-- ref: 110,7 --><lb/>
prosferome/nou pro\s th\n selh/nhn h)\ ta\ a)p' au)th=s r(eu/mata a)po&shy;<!-- ref: 110,8 --><lb/>
fero/mena o(malw=s a)naste/llontos e)pi\ tosou=ton e)f' o(/son ku/klw| <!-- ref: 110,9 --><lb/>
peristh=sai to\ nefoeide\s tou=to kai\ mh\ to\ para/pan diakri=nai, <!-- ref: 110,10 --><lb/>
h)\ kai\ to\n pe/ric au)th=s a)e/ra a)naste/llontos summe/trws pa/nto&shy;<!-- ref: 110,11 --><lb/>
qen ei)s to\ perifere\s to\ peri\ au)th\n kai\ paxumere\s peristh=sai. </s><s><!-- ref: 110,12 --><lb/>
o(/ gi/netai kata\ me/rh tina\ h)/toi e)/cwqen biasame/nou tino\s r(eu/&shy;<!-- ref: 111,1 --><lb/>
matos h)\ th=s qermasi/as e)pithdei/wn po/rwn e)pilambanome/nhs ei)s <!-- ref: 111,2 --><lb/>
to\ tou=to a)perga/sasqai. <!-- ref: 111,3 --><lb/>
</s></p><p><s>*komh=tai a)ste/res gi/nontai h)/toi puro\s e)n to/pois tisi\ dia\ <!-- ref: 111,4 --><lb/>
xro/nwn tinw=n e)n toi=s metew/rois suntrefome/nou perista/sews <!-- ref: 111,5 --><lb/>
ginome/nhs, h)\ i)di/an tina\ ki/nhsin dia\ xro/nwn tou= ou)ranou= i)/sxon&shy;<!-- ref: 111,6 --><lb/>
tos u(pe\r h(ma=s, w(/ste ta\ toiau=ta a)/stra a)nafanh=nai, h)\ au)&shy;<pb pagenum="269"/>ta\ e)n <!-- ref: 111,7 --><lb/>
xro/nois tisi\n o(rmh=sai dia/ tina peri/stasin kai\ ei)s tou\s kaq' <!-- ref: 111,8 --><lb/>
h(ma=s to/pous e)lqei=n kai\ e)kfanh= gene/sqai. </s><s>th/n te a)fa/nisin tou/&shy;<!-- ref: 111,9 --><lb/>
twn gi/nesqai para\ ta\s a)ntikeime/nas tau/tais ai)ti/as. <!-- ref: 111,10 --><lb/>
</s></p><p><s>*tina\ &lt;a)/stra&gt; stre/fetai au)tou=, o(\ sumbai/nei ou) mo/non tw=| to\ <!-- ref: 112,1 --><lb/>
me/ros tou=to tou= ko/smou e(sta/nai, peri\ o(\ to\ loipo\n stre/fetai,  <!-- ref: 112,2 --><lb/>
kaqa/per tine/s fasin, a)lla\ kai\ tw=| di/nhn a)e/ros e)/gkuklon au)&shy;<!-- ref: 112,3 --><lb/>
toi=s periesta/nai, h(\ kwlutikh\ gi/netai tou= peripolei=n w(s kai\ ta\ <!-- ref: 112,4 --><lb/>
a)/lla. </s><s>h)\ kai\ dia\ to\ e(ch=s me\n au)toi=s u(/lhn e)pithdei/an mh\ ei)=nai, <!-- ref: 112,5 --><lb/>
e)n de\ tou=tw| tw=| to/pw| e)n w(=| kei/mena qewrei=tai: kai\ kat' a)/llous <!-- ref: 112,6 --><lb/>
de\ plei/onas tro/pous tou=to dunato\n suntelei=sqai, e)a/n tis du/&shy;<!-- ref: 112,7 --><lb/>
nhtai to\ su/mfwnon toi=s fainome/nois sullogi/zesqai. <!-- ref: 112,8 --><lb/>
</s></p><p><s>*tina\ tw=n a)/strwn plana=sqai, ei) ou(/tw tai=s kinh/sesi xrw/me&shy;<!-- ref: 112,9 --><lb/>
na sumbai/nei, tina\ de\ mh\ [kinei=sqai] <!-- ref: 112,10 --><lb/>
e)nde/xetai me\n kai\ para\ <!-- ref: 113,1 --><lb/>
to\ ku/klw| kinou/mena e)c a)rxh=s ou(/tw kathnagka/sqai, w(/ste ta\ <!-- ref: 113,2 --><lb/>
me\n kata\ th\n au)th\n di=nan fe/resqai o(malh\n ou)=san, ta\ de\ kata\ <!-- ref: 113,3 --><lb/>
th\n a(/ma tisi\n a)nomali/ais xrwme/nhn: e)nde/xetai de\ kai\ kaq' ou(\s <!-- ref: 113,4 --><lb/>
to/pous fe/retai ou(= me\n parekta/seis a)e/ros ei)=nai o(malei=s e)pi\ to\ <!-- ref: 113,5 --><lb/>
au)to\ sunwqou/sas kata\ to\ e(ch=s o(malw=s te e)kkaou/sas, ou(= de\ <!-- ref: 113,6 --><lb/>
a)nwmalei=s ou(/tws, w(/ste ta\s qewroume/nas parallaga\s sunte&shy;<!-- ref: 113,7 --><lb/>
lei=sqai. </s><s>to\ de\ mi/an ai)ti/an tou/twn a)podido/nai, pleonaxw=s tw=n <!-- ref: 113,8 --><lb/>
fainome/nwn e)kkaloume/nwn, maniko\n kai\ ou) kaqhko/ntws prat&shy;<!-- ref: 113,9 --><lb/>
to/menon u(po\ tw=n th\n matai/an a)strologi/an e)zhlwko/twn kai\ <!-- ref: 113,10 --><lb/>
ei)s to\ keno\n ai)ti/as <pb pagenum="270"/>tinw=n a)podido/ntwn, o(/tan th\n qei/an fu/sin <!-- ref: 113,11 --><lb/>
mhqamh=| leitourgiw=n a)polu/wsi. <!-- ref: 113,12 --><lb/>
</s></p><p><s>*tina\ a)/stra u(poleipo/mena/ tinwn qewrei=sqai sumbai/nei kai\ <!-- ref: 114,1 --><lb/>
para\ to\ bradu/teron sumperife/resqai to\n au)to\n ku/klon pe&shy;<!-- ref: 114,2 --><lb/>
riio/nta, kai\ para\ to\ th\n e)nanti/an kinei=sqai a)ntispw/mena u(po\ <!-- ref: 114,3 --><lb/>
th=s au)th=s di/nhs, kai\ para\ to\ perife/resqai ta\ me\n dia\ plei/onos <!-- ref: 114,4 --><lb/>
to/pou, ta\ de\ di' e)la/ttonos, th\n au)th\n di=nan perikuklou=nta. </s><s><!-- ref: 114,5 --><lb/>
to\ de\ a(plw=s a)pofai/nesqai peri\ tou/twn kaqh=ko/n e)sti toi=s te&shy;<!-- ref: 114,6 --><lb/>
rateu/esqai/ ti pro\s tou\s pollou\s boulome/nois. <!-- ref: 114,7 --><lb/>
</s></p><p><s>*oi( lego/menoi a)ste/res e)kpi/ptein kai\ para\ me/ros kai\ para\ <!-- ref: 114,8 --><lb/>
tri=yin nefw=n du/nantai suntelei=sqai kai\ para\ e)/kptwsin, ou(= a)\n  <!-- ref: 114,9 --><lb/>
h( e)kpneuma/twsis ge/nhtai, kaqa/per kai\ e)pi\ tw=n a)strapw=n e)le/&shy;<!-- ref: 114,10 --><lb/>
gomen: <!-- ref: 114,11 --><lb/>
kai\ kata\ su/nodon de\ a)to/mwn puro\s a)potelestikw=n <!-- ref: 115,1 --><lb/>
sumfuli/as genome/nhs ei)s to\ tou=to tele/sai, kai\ kata\ ki/nhsin <!-- ref: 115,2 --><lb/>
ou(= a)\n h( o(rmh\ e)c a)rxh=s kata\ th\n su/nodon ge/nhtai: kai\ kata\ <!-- ref: 115,3 --><lb/>
pneuma/twn de\ sullogh\n e)n puknw/masi/n tisin [e)n] o)mixloeide/si <!-- ref: 115,4 --><lb/>
kai\ e)kpu/rwsin tou/twn dia\ th\n katei/lhsin ei)=t' e)pe/krhcin &lt;e)k&gt; <!-- ref: 115,5 --><lb/>
tw=n periexo/ntwn, kai\ e)f' o(\n a)\n to/pon h( o(rmh\ ge/nhtai th=s fora=s, <!-- ref: 115,6 --><lb/>
ei)s tou=ton ferome/nwn. </s><s>kai\ a)/lloi de\ tro/poi ei)s tou=to tele/sai <!-- ref: 115,7 --><lb/>
a)mu/qhtoi/ ei)sin. <!-- ref: 115,8 --><lb/>
</s></p><p><s>*ai( d' e)pishmasi/ai ai( gino/menai e)pi/ tisi zw/|ois kata\ sugku/&shy;<!-- ref: 115,9 --><lb/>
rhma gi/nontai tou= kairou=. </s><s>ou) ga\r ta\ zw=|a a)na/gkhn tina\ prosfe/&shy;<!-- ref: 115,10 --><lb/>
retai tou= a)potelesqh=nai xeimw=na, ou)de\ ka/qhtai/ tis qei/a fu/sis <!-- ref: 115,11 --><lb/>
parathrou=sa ta\s tw=n zw/|wn <pb pagenum="271"/>tou/twn e)co/dous ka)/peita ta\s e)pi&shy;<!-- ref: 115,12 --><lb/>
shmasi/as tau/tas e)pitelei=. </s><s><!-- ref: 115,13 --><lb/>
ou)de\ ga\r &lt;a)\n&gt; ei)s to\ tuxo\n zw=|on <!-- ref: 116,1 --><lb/>
ka)\n mikrw=| xarie/steron h)=|, h( toiau/th mwri/a e)kpe/soi, mh\ o(/ti ei)s <!-- ref: 116,2 --><lb/>
pantelh= eu)daimoni/an kekthme/non. <!-- ref: 116,3 --><lb/>
</s></p><p><s>*tau=ta de\ pa/nta, *puqo/kleis, mnhmo/neuson: kata\ polu/ te <!-- ref: 116,4 --><lb/>
ga\r tou= mu/qou e)kbh/sh| kai\ ta\ o(mogenh= tou/tois sunora=n dunh/sh|, <!-- ref: 116,5 --><lb/>
ma/lista de\ seauto\n a)po/dos ei)s th\n tw=n a)rxw=n kai\ a)peiri/as <!-- ref: 116,6 --><lb/>
kai\ tw=n suggenw=n tou/tois qewri/an, e)/ti te krithri/wn kai\ paqw=n, <!-- ref: 116,7 --><lb/>
kai\ ou(= e(/neken tau=ta e)klogizo/meqa. </s><s>tau=ta ga\r ma/lista sun&shy;<!-- ref: 116,8 --><lb/>
qewrou/mena r(a|di/ws ta\s peri\ tw=n kata\ me/ros ai)ti/as sunora=n <!-- ref: 116,9 --><lb/>
poih/sei. </s><s>oi( de\ tau=ta mh\ katagaph/santes h(=| ma/lista ou)/te &lt;a)\n&gt; <!-- ref: 116,10 --><lb/>
au)ta\ tau=ta kalw=s sunqewrh/saien ou)/te ou(= e(/neken dei= qewrei=n <!-- ref: 116,11 --><lb/>
tau=ta periepoih/santo.  <!-- ref: 116,12 --><lb/>
</s></p></chap></body><back/></text></archimedes>
